{"allFranceDataByDate":[{"code":"DEP-01","nom":"Ain","date":"2020-07-07","hospitalises":45,"reanimation":2,"nouvellesHospitalisations":0,"nouvellesReanimations":1,"deces":104,"gueris":431,"source":{"nom":"Santé publique France Data"},"sourceType":"sante-publique-france-data"},{"code":"DEP-02","nom":"Aisne","date":"2020-07-07","hospitalises":87,"reanimation":4,"nouvellesHospitalisations":4,"nouvellesReanimations":0,"deces":276,"gueris":1040,"source":{"nom":"Santé publique France Data"},"sourceType":"sante-publique-france-data"},{"code":"DEP-03","nom":"Allier","date":"2020-07-07","hospitalises":6,"reanimation":0,"nouvellesHospitalisations":0,"nouvellesReanimations":0,"deces":41,"gueris":198,"source":{"nom":"Santé publique France Data"},"sourceType":"sante-publique-france-data"},{"code":"DEP-04","nom":"Alpes-de-Haute-Provence","date":"2020-07-07","hospitalises":3,"reanimation":0,"nouvellesHospitalisations":0,"nouvellesReanimations":0,"deces":13,"gueris":130,"source":{"nom":"Santé publique France Data"},"sourceType":"sante-publique-france-data"},{"code":"DEP-05","nom":"Hautes-Alpes","date":"2020-07-07","hospitalises":7,"reanimation":0,"nouvellesHospitalisations":0,"nouvellesReanimations":0,"deces":18,"gueris":129,"source":{"nom":"Santé publique France Data"},"sourceType":"sante-publique-france-data"},{"code":"DEP-06","nom":"Alpes-Maritimes","date":"2020-07-07","hospitalises":32,"reanimation":1,"nouvellesHospitalisations":0,"nouvellesReanimations":0,"deces":188,"gueris":745,"source":{"nom":"Santé publique France Data"},"sourceType":"sante-publique-france-data"},{"code":"DEP-07","nom":"Ardèche","date":"2020-07-07","hospitalises":2,"reanimation":1,"nouvellesHospitalisations":0,"nouvellesReanimations":0,"deces":108,"gueris":439,"source":{"nom":"Santé publique France Data"},"sourceType":"sante-publique-france-data"},{"code":"DEP-08","nom":"Ardennes","date":"2020-07-07","hospitalises":9,"reanimation":2,"nouvellesHospitalisations":0,"nouvellesReanimations":0,"deces":60,"gueris":208,"source":{"nom":"Santé publique France Data"},"sourceType":"sante-publique-france-data"},{"code":"DEP-09","nom":"Ariège","date":"2020-07-07","hospitalises":1,"reanimation":1,"nouvellesHospitalisations":0,"nouvellesReanimations":0,"deces":2,"gueris":33,"source":{"nom":"Santé publique France Data"},"sourceType":"sante-publique-france-data"},{"code":"DEP-10","nom":"Aube","date":"2020-07-07","hospitalises":24,"reanimation":1,"nouvellesHospitalisations":0,"nouvellesReanimations":0,"deces":136,"gueris":621,"source":{"nom":"Santé publique France Data"},"sourceType":"sante-publique-france-data"},{"code":"DEP-11","nom":"Aude","date":"2020-07-07","hospitalises":2,"reanimation":0,"nouvellesHospitalisations":0,"nouvellesReanimations":0,"deces":59,"gueris":234,"source":{"nom":"Santé publique France Data"},"sourceType":"sante-publique-france-data"},{"code":"DEP-12","nom":"Aveyron","date":"2020-07-07","hospitalises":1,"reanimation":0,"nouvellesHospitalisations":0,"nouvellesReanimations":0,"deces":24,"gueris":143,"source":{"nom":"Santé publique France Data"},"sourceType":"sante-publique-france-data"},{"code":"DEP-13","nom":"Bouches-du-Rhône","date":"2020-07-07","hospitalises":335,"reanimation":18,"nouvellesHospitalisations":2,"nouvellesReanimations":0,"deces":560,"gueris":3264,"source":{"nom":"Santé publique France Data"},"sourceType":"sante-publique-france-data"},{"code":"DEP-14","nom":"Calvados","date":"2020-07-07","hospitalises":21,"reanimation":1,"nouvellesHospitalisations":1,"nouvellesReanimations":0,"deces":83,"gueris":320,"source":{"nom":"Santé publique France Data"},"sourceType":"sante-publique-france-data"},{"code":"DEP-15","nom":"Cantal","date":"2020-07-07","hospitalises":9,"reanimation":1,"nouvellesHospitalisations":0,"nouvellesReanimations":0,"deces":9,"gueris":49,"source":{"nom":"Santé publique France Data"},"sourceType":"sante-publique-france-data"},{"code":"DEP-16","nom":"Charente","date":"2020-07-07","hospitalises":2,"reanimation":1,"nouvellesHospitalisations":0,"nouvellesReanimations":0,"deces":13,"gueris":57,"source":{"nom":"Santé publique France Data"},"sourceType":"sante-publique-france-data"},{"code":"DEP-17","nom":"Charente-Maritime","date":"2020-07-07","hospitalises":6,"reanimation":0,"nouvellesHospitalisations":0,"nouvellesReanimations":0,"deces":51,"gueris":146,"source":{"nom":"Santé publique France Data"},"sourceType":"sante-publique-france-data"},{"code":"DEP-18","nom":"Cher","date":"2020-07-07","hospitalises":24,"reanimation":0,"nouvellesHospitalisations":0,"nouvellesReanimations":0,"deces":83,"gueris":179,"source":{"nom":"Santé publique France Data"},"sourceType":"sante-publique-france-data"},{"code":"DEP-19","nom":"Corrèze","date":"2020-07-07","hospitalises":0,"reanimation":0,"nouvellesHospitalisations":0,"nouvellesReanimations":0,"deces":37,"gueris":159,"source":{"nom":"Santé publique France Data"},"sourceType":"sante-publique-france-data"},{"code":"DEP-21","nom":"Côte-d'Or","date":"2020-07-07","hospitalises":6,"reanimation":1,"nouvellesHospitalisations":0,"nouvellesReanimations":0,"deces":250,"gueris":942,"source":{"nom":"Santé publique France Data"},"sourceType":"sante-publique-france-data"},{"code":"DEP-22","nom":"Côtes-d'Armor","date":"2020-07-07","hospitalises":9,"reanimation":0,"nouvellesHospitalisations":0,"nouvellesReanimations":0,"deces":38,"gueris":213,"source":{"nom":"Santé publique France Data"},"sourceType":"sante-publique-france-data"},{"code":"DEP-23","nom":"Creuse","date":"2020-07-07","hospitalises":3,"reanimation":1,"nouvellesHospitalisations":0,"nouvellesReanimations":0,"deces":13,"gueris":75,"source":{"nom":"Santé publique France Data"},"sourceType":"sante-publique-france-data"},{"code":"DEP-24","nom":"Dordogne","date":"2020-07-07","hospitalises":1,"reanimation":0,"nouvellesHospitalisations":0,"nouvellesReanimations":0,"deces":14,"gueris":97,"source":{"nom":"Santé publique France Data"},"sourceType":"sante-publique-france-data"},{"code":"DEP-25","nom":"Doubs","date":"2020-07-07","hospitalises":12,"reanimation":0,"nouvellesHospitalisations":2,"nouvellesReanimations":0,"deces":151,"gueris":629,"source":{"nom":"Santé publique France Data"},"sourceType":"sante-publique-france-data"},{"code":"DEP-26","nom":"Drôme","date":"2020-07-07","hospitalises":25,"reanimation":1,"nouvellesHospitalisations":0,"nouvellesReanimations":0,"deces":129,"gueris":506,"source":{"nom":"Santé publique France Data"},"sourceType":"sante-publique-france-data"},{"code":"DEP-27","nom":"Eure","date":"2020-07-07","hospitalises":34,"reanimation":0,"nouvellesHospitalisations":0,"nouvellesReanimations":0,"deces":84,"gueris":239,"source":{"nom":"Santé publique France Data"},"sourceType":"sante-publique-france-data"},{"code":"DEP-28","nom":"Eure-et-Loir","date":"2020-07-07","hospitalises":80,"reanimation":8,"nouvellesHospitalisations":0,"nouvellesReanimations":0,"deces":135,"gueris":528,"source":{"nom":"Santé publique France Data"},"sourceType":"sante-publique-france-data"},{"code":"DEP-29","nom":"Finistère","date":"2020-07-07","hospitalises":14,"reanimation":0,"nouvellesHospitalisations":1,"nouvellesReanimations":0,"deces":43,"gueris":175,"source":{"nom":"Santé publique France Data"},"sourceType":"sante-publique-france-data"},{"code":"DEP-2A","nom":"Corse-du-Sud","date":"2020-07-07","hospitalises":11,"reanimation":0,"nouvellesHospitalisations":0,"nouvellesReanimations":0,"deces":48,"gueris":139,"source":{"nom":"Santé publique France Data"},"sourceType":"sante-publique-france-data"},{"code":"DEP-2B","nom":"Haute-Corse","date":"2020-07-07","hospitalises":1,"reanimation":1,"nouvellesHospitalisations":0,"nouvellesReanimations":0,"deces":11,"gueris":108,"source":{"nom":"Santé publique France Data"},"sourceType":"sante-publique-france-data"},{"code":"DEP-30","nom":"Gard","date":"2020-07-07","hospitalises":12,"reanimation":1,"nouvellesHospitalisations":0,"nouvellesReanimations":0,"deces":97,"gueris":354,"source":{"nom":"Santé publique France Data"},"sourceType":"sante-publique-france-data"},{"code":"DEP-31","nom":"Haute-Garonne","date":"2020-07-07","hospitalises":26,"reanimation":4,"nouvellesHospitalisations":1,"nouvellesReanimations":1,"deces":73,"gueris":655,"source":{"nom":"Santé publique France Data"},"sourceType":"sante-publique-france-data"},{"code":"DEP-32","nom":"Gers","date":"2020-07-07","hospitalises":1,"reanimation":0,"nouvellesHospitalisations":0,"nouvellesReanimations":0,"deces":23,"gueris":88,"source":{"nom":"Santé publique France Data"},"sourceType":"sante-publique-france-data"},{"code":"DEP-33","nom":"Gironde","date":"2020-07-07","hospitalises":39,"reanimation":6,"nouvellesHospitalisations":1,"nouvellesReanimations":0,"deces":157,"gueris":946,"source":{"nom":"Santé publique France Data"},"sourceType":"sante-publique-france-data"},{"code":"DEP-34","nom":"Hérault","date":"2020-07-07","hospitalises":7,"reanimation":0,"nouvellesHospitalisations":2,"nouvellesReanimations":0,"deces":121,"gueris":703,"source":{"nom":"Santé publique France Data"},"sourceType":"sante-publique-france-data"},{"code":"DEP-35","nom":"Ille-et-Vilaine","date":"2020-07-07","hospitalises":33,"reanimation":2,"nouvellesHospitalisations":0,"nouvellesReanimations":0,"deces":86,"gueris":468,"source":{"nom":"Santé publique France Data"},"sourceType":"sante-publique-france-data"},{"code":"DEP-36","nom":"Indre","date":"2020-07-07","hospitalises":81,"reanimation":2,"nouvellesHospitalisations":0,"nouvellesReanimations":0,"deces":79,"gueris":110,"source":{"nom":"Santé publique France Data"},"sourceType":"sante-publique-france-data"},{"code":"DEP-37","nom":"Indre-et-Loire","date":"2020-07-07","hospitalises":59,"reanimation":2,"nouvellesHospitalisations":0,"nouvellesReanimations":0,"deces":85,"gueris":321,"source":{"nom":"Santé publique France Data"},"sourceType":"sante-publique-france-data"},{"code":"DEP-38","nom":"Isère","date":"2020-07-07","hospitalises":34,"reanimation":2,"nouvellesHospitalisations":0,"nouvellesReanimations":0,"deces":153,"gueris":691,"source":{"nom":"Santé publique France Data"},"sourceType":"sante-publique-france-data"},{"code":"DEP-39","nom":"Jura","date":"2020-07-07","hospitalises":5,"reanimation":0,"nouvellesHospitalisations":1,"nouvellesReanimations":0,"deces":60,"gueris":315,"source":{"nom":"Santé publique France Data"},"sourceType":"sante-publique-france-data"},{"code":"DEP-40","nom":"Landes","date":"2020-07-07","hospitalises":5,"reanimation":1,"nouvellesHospitalisations":0,"nouvellesReanimations":0,"deces":13,"gueris":73,"source":{"nom":"Santé publique France Data"},"sourceType":"sante-publique-france-data"},{"code":"DEP-41","nom":"Loir-et-Cher","date":"2020-07-07","hospitalises":87,"reanimation":0,"nouvellesHospitalisations":0,"nouvellesReanimations":0,"deces":63,"gueris":236,"source":{"nom":"Santé publique France Data"},"sourceType":"sante-publique-france-data"},{"code":"DEP-42","nom":"Loire","date":"2020-07-07","hospitalises":84,"reanimation":4,"nouvellesHospitalisations":0,"nouvellesReanimations":0,"deces":247,"gueris":959,"source":{"nom":"Santé publique France Data"},"sourceType":"sante-publique-france-data"},{"code":"DEP-43","nom":"Haute-Loire","date":"2020-07-07","hospitalises":1,"reanimation":0,"nouvellesHospitalisations":0,"nouvellesReanimations":0,"deces":18,"gueris":106,"source":{"nom":"Santé publique France Data"},"sourceType":"sante-publique-france-data"},{"code":"DEP-44","nom":"Loire-Atlantique","date":"2020-07-07","hospitalises":31,"reanimation":1,"nouvellesHospitalisations":0,"nouvellesReanimations":0,"deces":160,"gueris":702,"source":{"nom":"Santé publique France Data"},"sourceType":"sante-publique-france-data"},{"code":"DEP-45","nom":"Loiret","date":"2020-07-07","hospitalises":62,"reanimation":4,"nouvellesHospitalisations":0,"nouvellesReanimations":0,"deces":103,"gueris":599,"source":{"nom":"Santé publique France Data"},"sourceType":"sante-publique-france-data"},{"code":"DEP-46","nom":"Lot","date":"2020-07-07","hospitalises":0,"reanimation":0,"nouvellesHospitalisations":0,"nouvellesReanimations":0,"deces":22,"gueris":70,"source":{"nom":"Santé publique France Data"},"sourceType":"sante-publique-france-data"},{"code":"DEP-47","nom":"Lot-et-Garonne","date":"2020-07-07","hospitalises":1,"reanimation":0,"nouvellesHospitalisations":0,"nouvellesReanimations":0,"deces":11,"gueris":78,"source":{"nom":"Santé publique France Data"},"sourceType":"sante-publique-france-data"},{"code":"DEP-48","nom":"Lozère","date":"2020-07-07","hospitalises":0,"reanimation":0,"nouvellesHospitalisations":0,"nouvellesReanimations":0,"deces":1,"gueris":24,"source":{"nom":"Santé publique France Data"},"sourceType":"sante-publique-france-data"},{"code":"DEP-49","nom":"Maine-et-Loire","date":"2020-07-07","hospitalises":49,"reanimation":1,"nouvellesHospitalisations":2,"nouvellesReanimations":0,"deces":141,"gueris":604,"source":{"nom":"Santé publique France Data"},"sourceType":"sante-publique-france-data"},{"code":"DEP-50","nom":"Manche","date":"2020-07-07","hospitalises":35,"reanimation":0,"nouvellesHospitalisations":0,"nouvellesReanimations":0,"deces":47,"gueris":141,"source":{"nom":"Santé publique France Data"},"sourceType":"sante-publique-france-data"},{"code":"DEP-51","nom":"Marne","date":"2020-07-07","hospitalises":78,"reanimation":6,"nouvellesHospitalisations":0,"nouvellesReanimations":0,"deces":265,"gueris":995,"source":{"nom":"Santé publique France Data"},"sourceType":"sante-publique-france-data"},{"code":"DEP-52","nom":"Haute-Marne","date":"2020-07-07","hospitalises":23,"reanimation":0,"nouvellesHospitalisations":0,"nouvellesReanimations":0,"deces":88,"gueris":250,"source":{"nom":"Santé publique France Data"},"sourceType":"sante-publique-france-data"},{"code":"DEP-53","nom":"Mayenne","date":"2020-07-07","hospitalises":8,"reanimation":0,"nouvellesHospitalisations":1,"nouvellesReanimations":0,"deces":44,"gueris":182,"source":{"nom":"Santé publique France Data"},"sourceType":"sante-publique-france-data"},{"code":"DEP-54","nom":"Meurthe-et-Moselle","date":"2020-07-07","hospitalises":73,"reanimation":5,"nouvellesHospitalisations":1,"nouvellesReanimations":0,"deces":358,"gueris":1195,"source":{"nom":"Santé publique France Data"},"sourceType":"sante-publique-france-data"},{"code":"DEP-55","nom":"Meuse","date":"2020-07-07","hospitalises":4,"reanimation":0,"nouvellesHospitalisations":1,"nouvellesReanimations":0,"deces":103,"gueris":498,"source":{"nom":"Santé publique France Data"},"sourceType":"sante-publique-france-data"},{"code":"DEP-56","nom":"Morbihan","date":"2020-07-07","hospitalises":21,"reanimation":0,"nouvellesHospitalisations":0,"nouvellesReanimations":0,"deces":93,"gueris":428,"source":{"nom":"Santé publique France Data"},"sourceType":"sante-publique-france-data"},{"code":"DEP-57","nom":"Moselle","date":"2020-07-07","hospitalises":250,"reanimation":16,"nouvellesHospitalisations":0,"nouvellesReanimations":0,"deces":832,"gueris":2404,"source":{"nom":"Santé publique France Data"},"sourceType":"sante-publique-france-data"},{"code":"DEP-58","nom":"Nièvre","date":"2020-07-07","hospitalises":8,"reanimation":1,"nouvellesHospitalisations":0,"nouvellesReanimations":0,"deces":27,"gueris":90,"source":{"nom":"Santé publique France Data"},"sourceType":"sante-publique-france-data"},{"code":"DEP-59","nom":"Nord","date":"2020-07-07","hospitalises":351,"reanimation":19,"nouvellesHospitalisations":2,"nouvellesReanimations":1,"deces":630,"gueris":2268,"source":{"nom":"Santé publique France Data"},"sourceType":"sante-publique-france-data"},{"code":"DEP-60","nom":"Oise","date":"2020-07-07","hospitalises":219,"reanimation":5,"nouvellesHospitalisations":0,"nouvellesReanimations":0,"deces":411,"gueris":1092,"source":{"nom":"Santé publique France Data"},"sourceType":"sante-publique-france-data"},{"code":"DEP-61","nom":"Orne","date":"2020-07-07","hospitalises":33,"reanimation":2,"nouvellesHospitalisations":2,"nouvellesReanimations":0,"deces":39,"gueris":232,"source":{"nom":"Santé publique France Data"},"sourceType":"sante-publique-france-data"},{"code":"DEP-62","nom":"Pas-de-Calais","date":"2020-07-07","hospitalises":127,"reanimation":16,"nouvellesHospitalisations":1,"nouvellesReanimations":0,"deces":312,"gueris":1338,"source":{"nom":"Santé publique France Data"},"sourceType":"sante-publique-france-data"},{"code":"DEP-63","nom":"Puy-de-Dôme","date":"2020-07-07","hospitalises":18,"reanimation":1,"nouvellesHospitalisations":0,"nouvellesReanimations":0,"deces":42,"gueris":175,"source":{"nom":"Santé publique France Data"},"sourceType":"sante-publique-france-data"},{"code":"DEP-64","nom":"Pyrénées-Atlantiques","date":"2020-07-07","hospitalises":0,"reanimation":0,"nouvellesHospitalisations":0,"nouvellesReanimations":0,"deces":27,"gueris":224,"source":{"nom":"Santé publique France Data"},"sourceType":"sante-publique-france-data"},{"code":"DEP-65","nom":"Hautes-Pyrénées","date":"2020-07-07","hospitalises":3,"reanimation":2,"nouvellesHospitalisations":0,"nouvellesReanimations":0,"deces":27,"gueris":155,"source":{"nom":"Santé publique France Data"},"sourceType":"sante-publique-france-data"},{"code":"DEP-66","nom":"Pyrénées-Orientales","date":"2020-07-07","hospitalises":0,"reanimation":0,"nouvellesHospitalisations":0,"nouvellesReanimations":0,"deces":34,"gueris":278,"source":{"nom":"Santé publique France Data"},"sourceType":"sante-publique-france-data"},{"code":"DEP-67","nom":"Bas-Rhin","date":"2020-07-07","hospitalises":288,"reanimation":7,"nouvellesHospitalisations":1,"nouvellesReanimations":1,"deces":661,"gueris":2509,"source":{"nom":"Santé publique France Data"},"sourceType":"sante-publique-france-data"},{"code":"DEP-68","nom":"Haut-Rhin","date":"2020-07-07","hospitalises":224,"reanimation":15,"nouvellesHospitalisations":6,"nouvellesReanimations":4,"deces":817,"gueris":2894,"source":{"nom":"Santé publique France Data"},"sourceType":"sante-publique-france-data"},{"code":"DEP-69","nom":"Rhône","date":"2020-07-07","hospitalises":149,"reanimation":14,"nouvellesHospitalisations":3,"nouvellesReanimations":1,"deces":653,"gueris":2970,"source":{"nom":"Santé publique France Data"},"sourceType":"sante-publique-france-data"},{"code":"DEP-70","nom":"Haute-Saône","date":"2020-07-07","hospitalises":15,"reanimation":0,"nouvellesHospitalisations":0,"nouvellesReanimations":0,"deces":77,"gueris":294,"source":{"nom":"Santé publique France Data"},"sourceType":"sante-publique-france-data"},{"code":"DEP-71","nom":"Saône-et-Loire","date":"2020-07-07","hospitalises":24,"reanimation":2,"nouvellesHospitalisations":0,"nouvellesReanimations":0,"deces":201,"gueris":746,"source":{"nom":"Santé publique France Data"},"sourceType":"sante-publique-france-data"},{"code":"DEP-72","nom":"Sarthe","date":"2020-07-07","hospitalises":34,"reanimation":0,"nouvellesHospitalisations":0,"nouvellesReanimations":0,"deces":84,"gueris":359,"source":{"nom":"Santé publique France Data"},"sourceType":"sante-publique-france-data"},{"code":"DEP-73","nom":"Savoie","date":"2020-07-07","hospitalises":12,"reanimation":0,"nouvellesHospitalisations":1,"nouvellesReanimations":0,"deces":72,"gueris":401,"source":{"nom":"Santé publique France Data"},"sourceType":"sante-publique-france-data"},{"code":"DEP-74","nom":"Haute-Savoie","date":"2020-07-07","hospitalises":74,"reanimation":2,"nouvellesHospitalisations":0,"nouvellesReanimations":0,"deces":166,"gueris":849,"source":{"nom":"Santé publique France Data"},"sourceType":"sante-publique-france-data"},{"code":"DEP-75","nom":"Paris","date":"2020-07-07","hospitalises":420,"reanimation":49,"nouvellesHospitalisations":12,"nouvellesReanimations":2,"deces":1758,"gueris":6177,"source":{"nom":"Santé publique France Data"},"sourceType":"sante-publique-france-data"},{"code":"DEP-76","nom":"Seine-Maritime","date":"2020-07-07","hospitalises":92,"reanimation":4,"nouvellesHospitalisations":0,"nouvellesReanimations":0,"deces":181,"gueris":744,"source":{"nom":"Santé publique France Data"},"sourceType":"sante-publique-france-data"},{"code":"DEP-77","nom":"Seine-et-Marne","date":"2020-07-07","hospitalises":238,"reanimation":40,"nouvellesHospitalisations":9,"nouvellesReanimations":4,"deces":688,"gueris":2638,"source":{"nom":"Santé publique France Data"},"sourceType":"sante-publique-france-data"},{"code":"DEP-78","nom":"Yvelines","date":"2020-07-07","hospitalises":359,"reanimation":20,"nouvellesHospitalisations":5,"nouvellesReanimations":0,"deces":519,"gueris":2197,"source":{"nom":"Santé publique France Data"},"sourceType":"sante-publique-france-data"},{"code":"DEP-79","nom":"Deux-Sèvres","date":"2020-07-07","hospitalises":2,"reanimation":0,"nouvellesHospitalisations":0,"nouvellesReanimations":0,"deces":21,"gueris":66,"source":{"nom":"Santé publique France Data"},"sourceType":"sante-publique-france-data"},{"code":"DEP-80","nom":"Somme","date":"2020-07-07","hospitalises":65,"reanimation":5,"nouvellesHospitalisations":0,"nouvellesReanimations":0,"deces":223,"gueris":733,"source":{"nom":"Santé publique France Data"},"sourceType":"sante-publique-france-data"},{"code":"DEP-81","nom":"Tarn","date":"2020-07-07","hospitalises":2,"reanimation":1,"nouvellesHospitalisations":0,"nouvellesReanimations":0,"deces":23,"gueris":122,"source":{"nom":"Santé publique France Data"},"sourceType":"sante-publique-france-data"},{"code":"DEP-82","nom":"Tarn-et-Garonne","date":"2020-07-07","hospitalises":3,"reanimation":1,"nouvellesHospitalisations":0,"nouvellesReanimations":0,"deces":6,"gueris":42,"source":{"nom":"Santé publique France Data"},"sourceType":"sante-publique-france-data"},{"code":"DEP-83","nom":"Var","date":"2020-07-07","hospitalises":83,"reanimation":4,"nouvellesHospitalisations":1,"nouvellesReanimations":0,"deces":135,"gueris":971,"source":{"nom":"Santé publique France Data"},"sourceType":"sante-publique-france-data"},{"code":"DEP-84","nom":"Vaucluse","date":"2020-07-07","hospitalises":6,"reanimation":0,"nouvellesHospitalisations":0,"nouvellesReanimations":0,"deces":38,"gueris":257,"source":{"nom":"Santé publique France Data"},"sourceType":"sante-publique-france-data"},{"code":"DEP-85","nom":"Vendée","date":"2020-07-07","hospitalises":15,"reanimation":0,"nouvellesHospitalisations":2,"nouvellesReanimations":0,"deces":41,"gueris":256,"source":{"nom":"Santé publique France Data"},"sourceType":"sante-publique-france-data"},{"code":"DEP-86","nom":"Vienne","date":"2020-07-07","hospitalises":1,"reanimation":0,"nouvellesHospitalisations":0,"nouvellesReanimations":0,"deces":39,"gueris":148,"source":{"nom":"Santé publique France Data"},"sourceType":"sante-publique-france-data"},{"code":"DEP-87","nom":"Haute-Vienne","date":"2020-07-07","hospitalises":3,"reanimation":0,"nouvellesHospitalisations":1,"nouvellesReanimations":0,"deces":25,"gueris":129,"source":{"nom":"Santé publique France Data"},"sourceType":"sante-publique-france-data"},{"code":"DEP-88","nom":"Vosges","date":"2020-07-07","hospitalises":26,"reanimation":0,"nouvellesHospitalisations":1,"nouvellesReanimations":0,"deces":261,"gueris":720,"source":{"nom":"Santé publique France Data"},"sourceType":"sante-publique-france-data"},{"code":"DEP-89","nom":"Yonne","date":"2020-07-07","hospitalises":24,"reanimation":2,"nouvellesHospitalisations":2,"nouvellesReanimations":1,"deces":91,"gueris":354,"source":{"nom":"Santé publique France Data"},"sourceType":"sante-publique-france-data"},{"code":"DEP-90","nom":"Territoire de Belfort","date":"2020-07-07","hospitalises":11,"reanimation":0,"nouvellesHospitalisations":0,"nouvellesReanimations":0,"deces":187,"gueris":529,"source":{"nom":"Santé publique France Data"},"sourceType":"sante-publique-france-data"},{"code":"DEP-91","nom":"Essonne","date":"2020-07-07","hospitalises":291,"reanimation":21,"nouvellesHospitalisations":18,"nouvellesReanimations":0,"deces":537,"gueris":2399,"source":{"nom":"Santé publique France Data"},"sourceType":"sante-publique-france-data"},{"code":"DEP-92","nom":"Hauts-de-Seine","date":"2020-07-07","hospitalises":664,"reanimation":46,"nouvellesHospitalisations":2,"nouvellesReanimations":0,"deces":1081,"gueris":4366,"source":{"nom":"Santé publique France Data"},"sourceType":"sante-publique-france-data"},{"code":"DEP-93","nom":"Seine-Saint-Denis","date":"2020-07-07","hospitalises":655,"reanimation":58,"nouvellesHospitalisations":4,"nouvellesReanimations":1,"deces":990,"gueris":3691,"source":{"nom":"Santé publique France Data"},"sourceType":"sante-publique-france-data"},{"code":"DEP-94","nom":"Val-de-Marne","date":"2020-07-07","hospitalises":583,"reanimation":21,"nouvellesHospitalisations":4,"nouvellesReanimations":0,"deces":1196,"gueris":4068,"source":{"nom":"Santé publique France Data"},"sourceType":"sante-publique-france-data"},{"code":"DEP-95","nom":"Val-d'Oise","date":"2020-07-07","hospitalises":288,"reanimation":3,"nouvellesHospitalisations":2,"nouvellesReanimations":0,"deces":711,"gueris":2576,"source":{"nom":"Santé publique France Data"},"sourceType":"sante-publique-france-data"},{"code":"DEP-971","nom":"Guadeloupe","date":"2020-07-07","hospitalises":12,"reanimation":6,"nouvellesHospitalisations":0,"nouvellesReanimations":0,"deces":16,"gueris":80,"source":{"nom":"Santé publique France Data"},"sourceType":"sante-publique-france-data"},{"code":"DEP-972","nom":"Martinique","date":"2020-07-07","hospitalises":15,"reanimation":6,"nouvellesHospitalisations":0,"nouvellesReanimations":0,"deces":14,"gueris":90,"source":{"nom":"Santé publique France Data"},"sourceType":"sante-publique-france-data"},{"code":"DEP-973","nom":"Guyane","date":"2020-07-07","hospitalises":154,"reanimation":30,"nouvellesHospitalisations":24,"nouvellesReanimations":4,"deces":21,"gueris":517,"source":{"nom":"Santé publique France Data"},"sourceType":"sante-publique-france-data"},{"code":"DEP-974","nom":"La Réunion","date":"2020-07-07","hospitalises":21,"reanimation":3,"nouvellesHospitalisations":2,"nouvellesReanimations":0,"deces":3,"gueris":145,"source":{"nom":"Santé publique France Data"},"sourceType":"sante-publique-france-data"},{"code":"DEP-976","nom":"Mayotte","date":"2020-07-07","hospitalises":17,"reanimation":3,"nouvellesHospitalisations":2,"nouvellesReanimations":0,"deces":28,"gueris":384,"source":{"nom":"Santé publique France Data"},"sourceType":"sante-publique-france-data"},{"date":"2020-07-07","source":{"nom":"Ministère des Solidarités et de la Santé"},"sourceType":"ministere-sante","casConfirmes":168810,"deces":19457,"decesEhpad":10476,"hospitalises":7594,"reanimation":538,"gueris":77655,"casConfirmesEhpad":39256,"nouvellesHospitalisations":127,"nouvellesReanimations":21,"nom":"France","code":"FRA"},{"code":"FRA","nom":"France","date":"2020-07-07","hospitalises":7550,"reanimation":511,"nouvellesHospitalisations":127,"nouvellesReanimations":21,"deces":19437,"gueris":77644,"source":{"nom":"OpenCOVID19-fr"},"sourceType":"opencovid19-fr"},{"code":"REG-01","nom":"Guadeloupe","date":"2020-07-07","hospitalises":12,"reanimation":6,"nouvellesHospitalisations":0,"nouvellesReanimations":0,"deces":16,"gueris":80,"source":{"nom":"OpenCOVID19-fr"},"sourceType":"opencovid19-fr"},{"code":"REG-02","nom":"Martinique","date":"2020-07-07","hospitalises":15,"reanimation":6,"nouvellesHospitalisations":0,"nouvellesReanimations":0,"deces":14,"gueris":90,"source":{"nom":"OpenCOVID19-fr"},"sourceType":"opencovid19-fr"},{"code":"REG-03","nom":"Guyane","date":"2020-07-07","hospitalises":154,"reanimation":30,"nouvellesHospitalisations":24,"nouvellesReanimations":4,"deces":21,"gueris":517,"source":{"nom":"OpenCOVID19-fr"},"sourceType":"opencovid19-fr"},{"code":"REG-04","nom":"La Réunion","date":"2020-07-07","hospitalises":21,"reanimation":3,"nouvellesHospitalisations":2,"nouvellesReanimations":0,"deces":3,"gueris":145,"source":{"nom":"OpenCOVID19-fr"},"sourceType":"opencovid19-fr"},{"code":"REG-06","nom":"Mayotte","date":"2020-07-07","hospitalises":17,"reanimation":3,"nouvellesHospitalisations":2,"nouvellesReanimations":0,"deces":28,"gueris":384,"source":{"nom":"OpenCOVID19-fr"},"sourceType":"opencovid19-fr"},{"code":"REG-11","nom":"Île-de-France","date":"2020-07-07","hospitalises":3498,"reanimation":258,"nouvellesHospitalisations":56,"nouvellesReanimations":7,"deces":7480,"gueris":28112,"source":{"nom":"OpenCOVID19-fr"},"sourceType":"opencovid19-fr"},{"code":"REG-24","nom":"Centre-Val de Loire","date":"2020-07-07","hospitalises":393,"reanimation":16,"nouvellesHospitalisations":0,"nouvellesReanimations":0,"deces":548,"gueris":1973,"source":{"nom":"OpenCOVID19-fr"},"sourceType":"opencovid19-fr"},{"code":"REG-27","nom":"Bourgogne-Franche-Comté","date":"2020-07-07","hospitalises":105,"reanimation":6,"nouvellesHospitalisations":5,"nouvellesReanimations":1,"deces":1044,"gueris":3899,"source":{"nom":"OpenCOVID19-fr"},"sourceType":"opencovid19-fr"},{"code":"REG-28","nom":"Normandie","date":"2020-07-07","hospitalises":215,"reanimation":7,"nouvellesHospitalisations":3,"nouvellesReanimations":0,"deces":434,"gueris":1676,"source":{"nom":"OpenCOVID19-fr"},"sourceType":"opencovid19-fr"},{"code":"REG-32","nom":"Hauts-de-France","date":"2020-07-07","hospitalises":849,"reanimation":49,"nouvellesHospitalisations":7,"nouvellesReanimations":1,"deces":1852,"gueris":6471,"source":{"nom":"OpenCOVID19-fr"},"sourceType":"opencovid19-fr"},{"code":"REG-44","nom":"Grand Est","date":"2020-07-07","hospitalises":999,"reanimation":52,"nouvellesHospitalisations":10,"nouvellesReanimations":5,"deces":3581,"gueris":12294,"source":{"nom":"OpenCOVID19-fr"},"sourceType":"opencovid19-fr"},{"code":"REG-52","nom":"Pays de la Loire","date":"2020-07-07","hospitalises":137,"reanimation":2,"nouvellesHospitalisations":5,"nouvellesReanimations":0,"deces":470,"gueris":2103,"source":{"nom":"OpenCOVID19-fr"},"sourceType":"opencovid19-fr"},{"code":"REG-53","nom":"Bretagne","date":"2020-07-07","hospitalises":77,"reanimation":2,"nouvellesHospitalisations":1,"nouvellesReanimations":0,"deces":260,"gueris":1284,"source":{"nom":"OpenCOVID19-fr"},"sourceType":"opencovid19-fr"},{"code":"REG-75","nom":"Nouvelle-Aquitaine","date":"2020-07-07","hospitalises":63,"reanimation":9,"nouvellesHospitalisations":2,"nouvellesReanimations":0,"deces":421,"gueris":2198,"source":{"nom":"OpenCOVID19-fr"},"sourceType":"opencovid19-fr"},{"code":"REG-76","nom":"Occitanie","date":"2020-07-07","hospitalises":58,"reanimation":10,"nouvellesHospitalisations":3,"nouvellesReanimations":1,"deces":512,"gueris":2901,"source":{"nom":"OpenCOVID19-fr"},"sourceType":"opencovid19-fr"},{"code":"REG-84","nom":"Auvergne-Rhône-Alpes","date":"2020-07-07","hospitalises":459,"reanimation":28,"nouvellesHospitalisations":4,"nouvellesReanimations":2,"deces":1742,"gueris":7774,"source":{"nom":"OpenCOVID19-fr"},"sourceType":"opencovid19-fr"},{"code":"REG-93","nom":"Provence-Alpes-Côte d'Azur","date":"2020-07-07","hospitalises":466,"reanimation":23,"nouvellesHospitalisations":3,"nouvellesReanimations":0,"deces":952,"gueris":5496,"source":{"nom":"OpenCOVID19-fr"},"sourceType":"opencovid19-fr"},{"code":"REG-94","nom":"Corse","date":"2020-07-07","hospitalises":12,"reanimation":1,"nouvellesHospitalisations":0,"nouvellesReanimations":0,"deces":59,"gueris":247,"source":{"nom":"OpenCOVID19-fr"},"sourceType":"opencovid19-fr"}]}