{"allFranceDataByDate":[{"code":"DEP-01","nom":"Ain","date":"2020-08-06","hospitalises":27,"reanimation":1,"nouvellesHospitalisations":0,"nouvellesReanimations":0,"deces":105,"gueris":452,"source":{"nom":"Santé publique France Data"},"sourceType":"sante-publique-france-data"},{"code":"DEP-02","nom":"Aisne","date":"2020-08-06","hospitalises":47,"reanimation":6,"nouvellesHospitalisations":2,"nouvellesReanimations":0,"deces":280,"gueris":1100,"source":{"nom":"Santé publique France Data"},"sourceType":"sante-publique-france-data"},{"code":"DEP-03","nom":"Allier","date":"2020-08-06","hospitalises":2,"reanimation":0,"nouvellesHospitalisations":0,"nouvellesReanimations":0,"deces":41,"gueris":203,"source":{"nom":"Santé publique France Data"},"sourceType":"sante-publique-france-data"},{"code":"DEP-04","nom":"Alpes-de-Haute-Provence","date":"2020-08-06","hospitalises":2,"reanimation":0,"nouvellesHospitalisations":1,"nouvellesReanimations":0,"deces":13,"gueris":132,"source":{"nom":"Santé publique France Data"},"sourceType":"sante-publique-france-data"},{"code":"DEP-05","nom":"Hautes-Alpes","date":"2020-08-06","hospitalises":3,"reanimation":0,"nouvellesHospitalisations":0,"nouvellesReanimations":0,"deces":18,"gueris":134,"source":{"nom":"Santé publique France Data"},"sourceType":"sante-publique-france-data"},{"code":"DEP-06","nom":"Alpes-Maritimes","date":"2020-08-06","hospitalises":46,"reanimation":5,"nouvellesHospitalisations":4,"nouvellesReanimations":1,"deces":190,"gueris":784,"source":{"nom":"Santé publique France Data"},"sourceType":"sante-publique-france-data"},{"code":"DEP-07","nom":"Ardèche","date":"2020-08-06","hospitalises":2,"reanimation":1,"nouvellesHospitalisations":0,"nouvellesReanimations":0,"deces":110,"gueris":449,"source":{"nom":"Santé publique France Data"},"sourceType":"sante-publique-france-data"},{"code":"DEP-08","nom":"Ardennes","date":"2020-08-06","hospitalises":3,"reanimation":0,"nouvellesHospitalisations":0,"nouvellesReanimations":0,"deces":60,"gueris":219,"source":{"nom":"Santé publique France Data"},"sourceType":"sante-publique-france-data"},{"code":"DEP-09","nom":"Ariège","date":"2020-08-06","hospitalises":0,"reanimation":0,"nouvellesHospitalisations":0,"nouvellesReanimations":0,"deces":2,"gueris":33,"source":{"nom":"Santé publique France Data"},"sourceType":"sante-publique-france-data"},{"code":"DEP-10","nom":"Aube","date":"2020-08-06","hospitalises":21,"reanimation":0,"nouvellesHospitalisations":2,"nouvellesReanimations":0,"deces":137,"gueris":634,"source":{"nom":"Santé publique France Data"},"sourceType":"sante-publique-france-data"},{"code":"DEP-11","nom":"Aude","date":"2020-08-06","hospitalises":3,"reanimation":1,"nouvellesHospitalisations":0,"nouvellesReanimations":0,"deces":59,"gueris":236,"source":{"nom":"Santé publique France Data"},"sourceType":"sante-publique-france-data"},{"code":"DEP-12","nom":"Aveyron","date":"2020-08-06","hospitalises":4,"reanimation":1,"nouvellesHospitalisations":1,"nouvellesReanimations":0,"deces":24,"gueris":148,"source":{"nom":"Santé publique France Data"},"sourceType":"sante-publique-france-data"},{"code":"DEP-13","nom":"Bouches-du-Rhône","date":"2020-08-06","hospitalises":279,"reanimation":10,"nouvellesHospitalisations":2,"nouvellesReanimations":0,"deces":568,"gueris":3459,"source":{"nom":"Santé publique France Data"},"sourceType":"sante-publique-france-data"},{"code":"DEP-14","nom":"Calvados","date":"2020-08-06","hospitalises":12,"reanimation":1,"nouvellesHospitalisations":0,"nouvellesReanimations":0,"deces":85,"gueris":333,"source":{"nom":"Santé publique France Data"},"sourceType":"sante-publique-france-data"},{"code":"DEP-15","nom":"Cantal","date":"2020-08-06","hospitalises":5,"reanimation":1,"nouvellesHospitalisations":0,"nouvellesReanimations":0,"deces":9,"gueris":52,"source":{"nom":"Santé publique France Data"},"sourceType":"sante-publique-france-data"},{"code":"DEP-16","nom":"Charente","date":"2020-08-06","hospitalises":1,"reanimation":0,"nouvellesHospitalisations":0,"nouvellesReanimations":0,"deces":13,"gueris":61,"source":{"nom":"Santé publique France Data"},"sourceType":"sante-publique-france-data"},{"code":"DEP-17","nom":"Charente-Maritime","date":"2020-08-06","hospitalises":7,"reanimation":1,"nouvellesHospitalisations":0,"nouvellesReanimations":0,"deces":51,"gueris":149,"source":{"nom":"Santé publique France Data"},"sourceType":"sante-publique-france-data"},{"code":"DEP-18","nom":"Cher","date":"2020-08-06","hospitalises":5,"reanimation":0,"nouvellesHospitalisations":0,"nouvellesReanimations":0,"deces":85,"gueris":199,"source":{"nom":"Santé publique France Data"},"sourceType":"sante-publique-france-data"},{"code":"DEP-19","nom":"Corrèze","date":"2020-08-06","hospitalises":1,"reanimation":0,"nouvellesHospitalisations":0,"nouvellesReanimations":0,"deces":37,"gueris":159,"source":{"nom":"Santé publique France Data"},"sourceType":"sante-publique-france-data"},{"code":"DEP-21","nom":"Côte-d'Or","date":"2020-08-06","hospitalises":2,"reanimation":0,"nouvellesHospitalisations":1,"nouvellesReanimations":0,"deces":251,"gueris":956,"source":{"nom":"Santé publique France Data"},"sourceType":"sante-publique-france-data"},{"code":"DEP-22","nom":"Côtes-d'Armor","date":"2020-08-06","hospitalises":2,"reanimation":0,"nouvellesHospitalisations":0,"nouvellesReanimations":0,"deces":39,"gueris":227,"source":{"nom":"Santé publique France Data"},"sourceType":"sante-publique-france-data"},{"code":"DEP-23","nom":"Creuse","date":"2020-08-06","hospitalises":1,"reanimation":1,"nouvellesHospitalisations":0,"nouvellesReanimations":0,"deces":14,"gueris":81,"source":{"nom":"Santé publique France Data"},"sourceType":"sante-publique-france-data"},{"code":"DEP-24","nom":"Dordogne","date":"2020-08-06","hospitalises":1,"reanimation":0,"nouvellesHospitalisations":0,"nouvellesReanimations":0,"deces":14,"gueris":98,"source":{"nom":"Santé publique France Data"},"sourceType":"sante-publique-france-data"},{"code":"DEP-25","nom":"Doubs","date":"2020-08-06","hospitalises":1,"reanimation":0,"nouvellesHospitalisations":0,"nouvellesReanimations":0,"deces":151,"gueris":641,"source":{"nom":"Santé publique France Data"},"sourceType":"sante-publique-france-data"},{"code":"DEP-26","nom":"Drôme","date":"2020-08-06","hospitalises":7,"reanimation":2,"nouvellesHospitalisations":0,"nouvellesReanimations":0,"deces":129,"gueris":538,"source":{"nom":"Santé publique France Data"},"sourceType":"sante-publique-france-data"},{"code":"DEP-27","nom":"Eure","date":"2020-08-06","hospitalises":36,"reanimation":0,"nouvellesHospitalisations":3,"nouvellesReanimations":0,"deces":85,"gueris":249,"source":{"nom":"Santé publique France Data"},"sourceType":"sante-publique-france-data"},{"code":"DEP-28","nom":"Eure-et-Loir","date":"2020-08-06","hospitalises":18,"reanimation":3,"nouvellesHospitalisations":1,"nouvellesReanimations":0,"deces":142,"gueris":586,"source":{"nom":"Santé publique France Data"},"sourceType":"sante-publique-france-data"},{"code":"DEP-29","nom":"Finistère","date":"2020-08-06","hospitalises":6,"reanimation":0,"nouvellesHospitalisations":0,"nouvellesReanimations":0,"deces":44,"gueris":192,"source":{"nom":"Santé publique France Data"},"sourceType":"sante-publique-france-data"},{"code":"DEP-2A","nom":"Corse-du-Sud","date":"2020-08-06","hospitalises":7,"reanimation":0,"nouvellesHospitalisations":0,"nouvellesReanimations":0,"deces":48,"gueris":144,"source":{"nom":"Santé publique France Data"},"sourceType":"sante-publique-france-data"},{"code":"DEP-2B","nom":"Haute-Corse","date":"2020-08-06","hospitalises":0,"reanimation":0,"nouvellesHospitalisations":0,"nouvellesReanimations":0,"deces":11,"gueris":108,"source":{"nom":"Santé publique France Data"},"sourceType":"sante-publique-france-data"},{"code":"DEP-30","nom":"Gard","date":"2020-08-06","hospitalises":6,"reanimation":1,"nouvellesHospitalisations":0,"nouvellesReanimations":0,"deces":97,"gueris":367,"source":{"nom":"Santé publique France Data"},"sourceType":"sante-publique-france-data"},{"code":"DEP-31","nom":"Haute-Garonne","date":"2020-08-06","hospitalises":22,"reanimation":5,"nouvellesHospitalisations":0,"nouvellesReanimations":0,"deces":73,"gueris":682,"source":{"nom":"Santé publique France Data"},"sourceType":"sante-publique-france-data"},{"code":"DEP-32","nom":"Gers","date":"2020-08-06","hospitalises":1,"reanimation":0,"nouvellesHospitalisations":0,"nouvellesReanimations":0,"deces":23,"gueris":88,"source":{"nom":"Santé publique France Data"},"sourceType":"sante-publique-france-data"},{"code":"DEP-33","nom":"Gironde","date":"2020-08-06","hospitalises":29,"reanimation":6,"nouvellesHospitalisations":2,"nouvellesReanimations":0,"deces":159,"gueris":980,"source":{"nom":"Santé publique France Data"},"sourceType":"sante-publique-france-data"},{"code":"DEP-34","nom":"Hérault","date":"2020-08-06","hospitalises":4,"reanimation":0,"nouvellesHospitalisations":1,"nouvellesReanimations":0,"deces":123,"gueris":719,"source":{"nom":"Santé publique France Data"},"sourceType":"sante-publique-france-data"},{"code":"DEP-35","nom":"Ille-et-Vilaine","date":"2020-08-06","hospitalises":32,"reanimation":6,"nouvellesHospitalisations":0,"nouvellesReanimations":1,"deces":88,"gueris":493,"source":{"nom":"Santé publique France Data"},"sourceType":"sante-publique-france-data"},{"code":"DEP-36","nom":"Indre","date":"2020-08-06","hospitalises":41,"reanimation":1,"nouvellesHospitalisations":0,"nouvellesReanimations":0,"deces":80,"gueris":150,"source":{"nom":"Santé publique France Data"},"sourceType":"sante-publique-france-data"},{"code":"DEP-37","nom":"Indre-et-Loire","date":"2020-08-06","hospitalises":23,"reanimation":1,"nouvellesHospitalisations":1,"nouvellesReanimations":0,"deces":87,"gueris":362,"source":{"nom":"Santé publique France Data"},"sourceType":"sante-publique-france-data"},{"code":"DEP-38","nom":"Isère","date":"2020-08-06","hospitalises":25,"reanimation":2,"nouvellesHospitalisations":1,"nouvellesReanimations":1,"deces":153,"gueris":712,"source":{"nom":"Santé publique France Data"},"sourceType":"sante-publique-france-data"},{"code":"DEP-39","nom":"Jura","date":"2020-08-06","hospitalises":0,"reanimation":0,"nouvellesHospitalisations":0,"nouvellesReanimations":0,"deces":60,"gueris":328,"source":{"nom":"Santé publique France Data"},"sourceType":"sante-publique-france-data"},{"code":"DEP-40","nom":"Landes","date":"2020-08-06","hospitalises":2,"reanimation":0,"nouvellesHospitalisations":0,"nouvellesReanimations":0,"deces":13,"gueris":76,"source":{"nom":"Santé publique France Data"},"sourceType":"sante-publique-france-data"},{"code":"DEP-41","nom":"Loir-et-Cher","date":"2020-08-06","hospitalises":37,"reanimation":0,"nouvellesHospitalisations":0,"nouvellesReanimations":0,"deces":63,"gueris":306,"source":{"nom":"Santé publique France Data"},"sourceType":"sante-publique-france-data"},{"code":"DEP-42","nom":"Loire","date":"2020-08-06","hospitalises":74,"reanimation":2,"nouvellesHospitalisations":0,"nouvellesReanimations":0,"deces":248,"gueris":979,"source":{"nom":"Santé publique France Data"},"sourceType":"sante-publique-france-data"},{"code":"DEP-43","nom":"Haute-Loire","date":"2020-08-06","hospitalises":1,"reanimation":0,"nouvellesHospitalisations":0,"nouvellesReanimations":0,"deces":18,"gueris":107,"source":{"nom":"Santé publique France Data"},"sourceType":"sante-publique-france-data"},{"code":"DEP-44","nom":"Loire-Atlantique","date":"2020-08-06","hospitalises":12,"reanimation":2,"nouvellesHospitalisations":6,"nouvellesReanimations":2,"deces":164,"gueris":745,"source":{"nom":"Santé publique France Data"},"sourceType":"sante-publique-france-data"},{"code":"DEP-45","nom":"Loiret","date":"2020-08-06","hospitalises":31,"reanimation":4,"nouvellesHospitalisations":0,"nouvellesReanimations":0,"deces":103,"gueris":636,"source":{"nom":"Santé publique France Data"},"sourceType":"sante-publique-france-data"},{"code":"DEP-46","nom":"Lot","date":"2020-08-06","hospitalises":0,"reanimation":0,"nouvellesHospitalisations":0,"nouvellesReanimations":0,"deces":22,"gueris":70,"source":{"nom":"Santé publique France Data"},"sourceType":"sante-publique-france-data"},{"code":"DEP-47","nom":"Lot-et-Garonne","date":"2020-08-06","hospitalises":2,"reanimation":1,"nouvellesHospitalisations":0,"nouvellesReanimations":0,"deces":11,"gueris":79,"source":{"nom":"Santé publique France Data"},"sourceType":"sante-publique-france-data"},{"code":"DEP-48","nom":"Lozère","date":"2020-08-06","hospitalises":0,"reanimation":0,"nouvellesHospitalisations":0,"nouvellesReanimations":0,"deces":1,"gueris":24,"source":{"nom":"Santé publique France Data"},"sourceType":"sante-publique-france-data"},{"code":"DEP-49","nom":"Maine-et-Loire","date":"2020-08-06","hospitalises":30,"reanimation":4,"nouvellesHospitalisations":2,"nouvellesReanimations":1,"deces":141,"gueris":647,"source":{"nom":"Santé publique France Data"},"sourceType":"sante-publique-france-data"},{"code":"DEP-50","nom":"Manche","date":"2020-08-06","hospitalises":24,"reanimation":0,"nouvellesHospitalisations":0,"nouvellesReanimations":0,"deces":48,"gueris":153,"source":{"nom":"Santé publique France Data"},"sourceType":"sante-publique-france-data"},{"code":"DEP-51","nom":"Marne","date":"2020-08-06","hospitalises":64,"reanimation":6,"nouvellesHospitalisations":1,"nouvellesReanimations":1,"deces":267,"gueris":1013,"source":{"nom":"Santé publique France Data"},"sourceType":"sante-publique-france-data"},{"code":"DEP-52","nom":"Haute-Marne","date":"2020-08-06","hospitalises":19,"reanimation":0,"nouvellesHospitalisations":0,"nouvellesReanimations":0,"deces":90,"gueris":258,"source":{"nom":"Santé publique France Data"},"sourceType":"sante-publique-france-data"},{"code":"DEP-53","nom":"Mayenne","date":"2020-08-06","hospitalises":14,"reanimation":3,"nouvellesHospitalisations":3,"nouvellesReanimations":1,"deces":46,"gueris":221,"source":{"nom":"Santé publique France Data"},"sourceType":"sante-publique-france-data"},{"code":"DEP-54","nom":"Meurthe-et-Moselle","date":"2020-08-06","hospitalises":52,"reanimation":1,"nouvellesHospitalisations":0,"nouvellesReanimations":0,"deces":361,"gueris":1244,"source":{"nom":"Santé publique France Data"},"sourceType":"sante-publique-france-data"},{"code":"DEP-55","nom":"Meuse","date":"2020-08-06","hospitalises":2,"reanimation":0,"nouvellesHospitalisations":0,"nouvellesReanimations":0,"deces":103,"gueris":502,"source":{"nom":"Santé publique France Data"},"sourceType":"sante-publique-france-data"},{"code":"DEP-56","nom":"Morbihan","date":"2020-08-06","hospitalises":20,"reanimation":1,"nouvellesHospitalisations":0,"nouvellesReanimations":0,"deces":96,"gueris":434,"source":{"nom":"Santé publique France Data"},"sourceType":"sante-publique-france-data"},{"code":"DEP-57","nom":"Moselle","date":"2020-08-06","hospitalises":120,"reanimation":3,"nouvellesHospitalisations":3,"nouvellesReanimations":0,"deces":845,"gueris":2543,"source":{"nom":"Santé publique France Data"},"sourceType":"sante-publique-france-data"},{"code":"DEP-58","nom":"Nièvre","date":"2020-08-06","hospitalises":0,"reanimation":0,"nouvellesHospitalisations":0,"nouvellesReanimations":0,"deces":28,"gueris":99,"source":{"nom":"Santé publique France Data"},"sourceType":"sante-publique-france-data"},{"code":"DEP-59","nom":"Nord","date":"2020-08-06","hospitalises":181,"reanimation":21,"nouvellesHospitalisations":4,"nouvellesReanimations":1,"deces":668,"gueris":2572,"source":{"nom":"Santé publique France Data"},"sourceType":"sante-publique-france-data"},{"code":"DEP-60","nom":"Oise","date":"2020-08-06","hospitalises":135,"reanimation":4,"nouvellesHospitalisations":1,"nouvellesReanimations":0,"deces":418,"gueris":1197,"source":{"nom":"Santé publique France Data"},"sourceType":"sante-publique-france-data"},{"code":"DEP-61","nom":"Orne","date":"2020-08-06","hospitalises":23,"reanimation":2,"nouvellesHospitalisations":0,"nouvellesReanimations":0,"deces":40,"gueris":246,"source":{"nom":"Santé publique France Data"},"sourceType":"sante-publique-france-data"},{"code":"DEP-62","nom":"Pas-de-Calais","date":"2020-08-06","hospitalises":81,"reanimation":9,"nouvellesHospitalisations":1,"nouvellesReanimations":0,"deces":320,"gueris":1414,"source":{"nom":"Santé publique France Data"},"sourceType":"sante-publique-france-data"},{"code":"DEP-63","nom":"Puy-de-Dôme","date":"2020-08-06","hospitalises":16,"reanimation":0,"nouvellesHospitalisations":1,"nouvellesReanimations":0,"deces":43,"gueris":179,"source":{"nom":"Santé publique France Data"},"sourceType":"sante-publique-france-data"},{"code":"DEP-64","nom":"Pyrénées-Atlantiques","date":"2020-08-06","hospitalises":1,"reanimation":0,"nouvellesHospitalisations":0,"nouvellesReanimations":0,"deces":27,"gueris":227,"source":{"nom":"Santé publique France Data"},"sourceType":"sante-publique-france-data"},{"code":"DEP-65","nom":"Hautes-Pyrénées","date":"2020-08-06","hospitalises":3,"reanimation":3,"nouvellesHospitalisations":1,"nouvellesReanimations":1,"deces":27,"gueris":158,"source":{"nom":"Santé publique France Data"},"sourceType":"sante-publique-france-data"},{"code":"DEP-66","nom":"Pyrénées-Orientales","date":"2020-08-06","hospitalises":0,"reanimation":0,"nouvellesHospitalisations":0,"nouvellesReanimations":0,"deces":34,"gueris":282,"source":{"nom":"Santé publique France Data"},"sourceType":"sante-publique-france-data"},{"code":"DEP-67","nom":"Bas-Rhin","date":"2020-08-06","hospitalises":136,"reanimation":3,"nouvellesHospitalisations":1,"nouvellesReanimations":0,"deces":671,"gueris":2674,"source":{"nom":"Santé publique France Data"},"sourceType":"sante-publique-france-data"},{"code":"DEP-68","nom":"Haut-Rhin","date":"2020-08-06","hospitalises":145,"reanimation":3,"nouvellesHospitalisations":3,"nouvellesReanimations":0,"deces":825,"gueris":3008,"source":{"nom":"Santé publique France Data"},"sourceType":"sante-publique-france-data"},{"code":"DEP-69","nom":"Rhône","date":"2020-08-06","hospitalises":81,"reanimation":8,"nouvellesHospitalisations":5,"nouvellesReanimations":0,"deces":664,"gueris":3120,"source":{"nom":"Santé publique France Data"},"sourceType":"sante-publique-france-data"},{"code":"DEP-70","nom":"Haute-Saône","date":"2020-08-06","hospitalises":0,"reanimation":0,"nouvellesHospitalisations":0,"nouvellesReanimations":0,"deces":77,"gueris":309,"source":{"nom":"Santé publique France Data"},"sourceType":"sante-publique-france-data"},{"code":"DEP-71","nom":"Saône-et-Loire","date":"2020-08-06","hospitalises":3,"reanimation":1,"nouvellesHospitalisations":0,"nouvellesReanimations":0,"deces":201,"gueris":785,"source":{"nom":"Santé publique France Data"},"sourceType":"sante-publique-france-data"},{"code":"DEP-72","nom":"Sarthe","date":"2020-08-06","hospitalises":37,"reanimation":3,"nouvellesHospitalisations":3,"nouvellesReanimations":0,"deces":85,"gueris":389,"source":{"nom":"Santé publique France Data"},"sourceType":"sante-publique-france-data"},{"code":"DEP-73","nom":"Savoie","date":"2020-08-06","hospitalises":3,"reanimation":0,"nouvellesHospitalisations":0,"nouvellesReanimations":0,"deces":73,"gueris":423,"source":{"nom":"Santé publique France Data"},"sourceType":"sante-publique-france-data"},{"code":"DEP-74","nom":"Haute-Savoie","date":"2020-08-06","hospitalises":58,"reanimation":1,"nouvellesHospitalisations":0,"nouvellesReanimations":0,"deces":168,"gueris":884,"source":{"nom":"Santé publique France Data"},"sourceType":"sante-publique-france-data"},{"code":"DEP-75","nom":"Paris","date":"2020-08-06","hospitalises":273,"reanimation":36,"nouvellesHospitalisations":13,"nouvellesReanimations":4,"deces":1784,"gueris":6453,"source":{"nom":"Santé publique France Data"},"sourceType":"sante-publique-france-data"},{"code":"DEP-76","nom":"Seine-Maritime","date":"2020-08-06","hospitalises":31,"reanimation":1,"nouvellesHospitalisations":0,"nouvellesReanimations":0,"deces":184,"gueris":826,"source":{"nom":"Santé publique France Data"},"sourceType":"sante-publique-france-data"},{"code":"DEP-77","nom":"Seine-et-Marne","date":"2020-08-06","hospitalises":193,"reanimation":27,"nouvellesHospitalisations":2,"nouvellesReanimations":0,"deces":706,"gueris":2732,"source":{"nom":"Santé publique France Data"},"sourceType":"sante-publique-france-data"},{"code":"DEP-78","nom":"Yvelines","date":"2020-08-06","hospitalises":277,"reanimation":22,"nouvellesHospitalisations":6,"nouvellesReanimations":1,"deces":528,"gueris":2350,"source":{"nom":"Santé publique France Data"},"sourceType":"sante-publique-france-data"},{"code":"DEP-79","nom":"Deux-Sèvres","date":"2020-08-06","hospitalises":1,"reanimation":0,"nouvellesHospitalisations":0,"nouvellesReanimations":0,"deces":22,"gueris":68,"source":{"nom":"Santé publique France Data"},"sourceType":"sante-publique-france-data"},{"code":"DEP-80","nom":"Somme","date":"2020-08-06","hospitalises":40,"reanimation":1,"nouvellesHospitalisations":0,"nouvellesReanimations":0,"deces":233,"gueris":756,"source":{"nom":"Santé publique France Data"},"sourceType":"sante-publique-france-data"},{"code":"DEP-81","nom":"Tarn","date":"2020-08-06","hospitalises":3,"reanimation":1,"nouvellesHospitalisations":0,"nouvellesReanimations":0,"deces":23,"gueris":123,"source":{"nom":"Santé publique France Data"},"sourceType":"sante-publique-france-data"},{"code":"DEP-82","nom":"Tarn-et-Garonne","date":"2020-08-06","hospitalises":3,"reanimation":0,"nouvellesHospitalisations":0,"nouvellesReanimations":0,"deces":7,"gueris":43,"source":{"nom":"Santé publique France Data"},"sourceType":"sante-publique-france-data"},{"code":"DEP-83","nom":"Var","date":"2020-08-06","hospitalises":50,"reanimation":2,"nouvellesHospitalisations":0,"nouvellesReanimations":0,"deces":140,"gueris":1015,"source":{"nom":"Santé publique France Data"},"sourceType":"sante-publique-france-data"},{"code":"DEP-84","nom":"Vaucluse","date":"2020-08-06","hospitalises":7,"reanimation":2,"nouvellesHospitalisations":0,"nouvellesReanimations":0,"deces":38,"gueris":262,"source":{"nom":"Santé publique France Data"},"sourceType":"sante-publique-france-data"},{"code":"DEP-85","nom":"Vendée","date":"2020-08-06","hospitalises":8,"reanimation":0,"nouvellesHospitalisations":0,"nouvellesReanimations":0,"deces":42,"gueris":270,"source":{"nom":"Santé publique France Data"},"sourceType":"sante-publique-france-data"},{"code":"DEP-86","nom":"Vienne","date":"2020-08-06","hospitalises":1,"reanimation":0,"nouvellesHospitalisations":0,"nouvellesReanimations":0,"deces":40,"gueris":149,"source":{"nom":"Santé publique France Data"},"sourceType":"sante-publique-france-data"},{"code":"DEP-87","nom":"Haute-Vienne","date":"2020-08-06","hospitalises":3,"reanimation":0,"nouvellesHospitalisations":0,"nouvellesReanimations":0,"deces":25,"gueris":133,"source":{"nom":"Santé publique France Data"},"sourceType":"sante-publique-france-data"},{"code":"DEP-88","nom":"Vosges","date":"2020-08-06","hospitalises":7,"reanimation":0,"nouvellesHospitalisations":0,"nouvellesReanimations":0,"deces":266,"gueris":743,"source":{"nom":"Santé publique France Data"},"sourceType":"sante-publique-france-data"},{"code":"DEP-89","nom":"Yonne","date":"2020-08-06","hospitalises":14,"reanimation":3,"nouvellesHospitalisations":4,"nouvellesReanimations":0,"deces":94,"gueris":390,"source":{"nom":"Santé publique France Data"},"sourceType":"sante-publique-france-data"},{"code":"DEP-90","nom":"Territoire de Belfort","date":"2020-08-06","hospitalises":4,"reanimation":0,"nouvellesHospitalisations":0,"nouvellesReanimations":0,"deces":200,"gueris":558,"source":{"nom":"Santé publique France Data"},"sourceType":"sante-publique-france-data"},{"code":"DEP-91","nom":"Essonne","date":"2020-08-06","hospitalises":242,"reanimation":15,"nouvellesHospitalisations":0,"nouvellesReanimations":0,"deces":538,"gueris":2485,"source":{"nom":"Santé publique France Data"},"sourceType":"sante-publique-france-data"},{"code":"DEP-92","nom":"Hauts-de-Seine","date":"2020-08-06","hospitalises":550,"reanimation":39,"nouvellesHospitalisations":9,"nouvellesReanimations":1,"deces":1096,"gueris":4598,"source":{"nom":"Santé publique France Data"},"sourceType":"sante-publique-france-data"},{"code":"DEP-93","nom":"Seine-Saint-Denis","date":"2020-08-06","hospitalises":460,"reanimation":23,"nouvellesHospitalisations":9,"nouvellesReanimations":1,"deces":1012,"gueris":3960,"source":{"nom":"Santé publique France Data"},"sourceType":"sante-publique-france-data"},{"code":"DEP-94","nom":"Val-de-Marne","date":"2020-08-06","hospitalises":319,"reanimation":18,"nouvellesHospitalisations":12,"nouvellesReanimations":4,"deces":1212,"gueris":4467,"source":{"nom":"Santé publique France Data"},"sourceType":"sante-publique-france-data"},{"code":"DEP-95","nom":"Val-d'Oise","date":"2020-08-06","hospitalises":229,"reanimation":5,"nouvellesHospitalisations":3,"nouvellesReanimations":0,"deces":719,"gueris":2709,"source":{"nom":"Santé publique France Data"},"sourceType":"sante-publique-france-data"},{"code":"DEP-971","nom":"Guadeloupe","date":"2020-08-06","hospitalises":3,"reanimation":0,"nouvellesHospitalisations":0,"nouvellesReanimations":0,"deces":17,"gueris":86,"source":{"nom":"Santé publique France Data"},"sourceType":"sante-publique-france-data"},{"code":"DEP-972","nom":"Martinique","date":"2020-08-06","hospitalises":6,"reanimation":2,"nouvellesHospitalisations":1,"nouvellesReanimations":0,"deces":16,"gueris":97,"source":{"nom":"Santé publique France Data"},"sourceType":"sante-publique-france-data"},{"code":"DEP-973","nom":"Guyane","date":"2020-08-06","hospitalises":128,"reanimation":24,"nouvellesHospitalisations":24,"nouvellesReanimations":0,"deces":44,"gueris":1154,"source":{"nom":"Santé publique France Data"},"sourceType":"sante-publique-france-data"},{"code":"DEP-974","nom":"La Réunion","date":"2020-08-06","hospitalises":18,"reanimation":3,"nouvellesHospitalisations":1,"nouvellesReanimations":0,"deces":5,"gueris":165,"source":{"nom":"Santé publique France Data"},"sourceType":"sante-publique-france-data"},{"code":"DEP-976","nom":"Mayotte","date":"2020-08-06","hospitalises":8,"reanimation":1,"nouvellesHospitalisations":0,"nouvellesReanimations":0,"deces":28,"gueris":427,"source":{"nom":"Santé publique France Data"},"sourceType":"sante-publique-france-data"},{"date":"2020-08-06","source":{"nom":"Ministère des Solidarités et de la Santé"},"sourceType":"ministere-sante","casConfirmes":195633,"deces":19806,"decesEhpad":10506,"hospitalises":5060,"reanimation":390,"gueris":82670,"casConfirmesEhpad":39645,"nouvellesHospitalisations":141,"nouvellesReanimations":21,"nom":"France","code":"FRA"},{"code":"FRA","nom":"France","date":"2020-08-06","hospitalises":5019,"reanimation":366,"nouvellesHospitalisations":141,"nouvellesReanimations":21,"deces":19786,"gueris":82659,"source":{"nom":"OpenCOVID19-fr"},"sourceType":"opencovid19-fr"},{"code":"REG-01","nom":"Guadeloupe","date":"2020-08-06","hospitalises":3,"reanimation":0,"nouvellesHospitalisations":0,"nouvellesReanimations":0,"deces":17,"gueris":86,"source":{"nom":"OpenCOVID19-fr"},"sourceType":"opencovid19-fr"},{"code":"REG-02","nom":"Martinique","date":"2020-08-06","hospitalises":6,"reanimation":2,"nouvellesHospitalisations":1,"nouvellesReanimations":0,"deces":16,"gueris":97,"source":{"nom":"OpenCOVID19-fr"},"sourceType":"opencovid19-fr"},{"code":"REG-03","nom":"Guyane","date":"2020-08-06","hospitalises":128,"reanimation":24,"nouvellesHospitalisations":24,"nouvellesReanimations":0,"deces":44,"gueris":1154,"source":{"nom":"OpenCOVID19-fr"},"sourceType":"opencovid19-fr"},{"code":"REG-04","nom":"La Réunion","date":"2020-08-06","hospitalises":18,"reanimation":3,"nouvellesHospitalisations":1,"nouvellesReanimations":0,"deces":5,"gueris":165,"source":{"nom":"OpenCOVID19-fr"},"sourceType":"opencovid19-fr"},{"code":"REG-06","nom":"Mayotte","date":"2020-08-06","hospitalises":8,"reanimation":1,"nouvellesHospitalisations":0,"nouvellesReanimations":0,"deces":28,"gueris":427,"source":{"nom":"OpenCOVID19-fr"},"sourceType":"opencovid19-fr"},{"code":"REG-11","nom":"Île-de-France","date":"2020-08-06","hospitalises":2543,"reanimation":185,"nouvellesHospitalisations":54,"nouvellesReanimations":11,"deces":7595,"gueris":29754,"source":{"nom":"OpenCOVID19-fr"},"sourceType":"opencovid19-fr"},{"code":"REG-24","nom":"Centre-Val de Loire","date":"2020-08-06","hospitalises":155,"reanimation":9,"nouvellesHospitalisations":2,"nouvellesReanimations":0,"deces":560,"gueris":2239,"source":{"nom":"OpenCOVID19-fr"},"sourceType":"opencovid19-fr"},{"code":"REG-27","nom":"Bourgogne-Franche-Comté","date":"2020-08-06","hospitalises":24,"reanimation":4,"nouvellesHospitalisations":5,"nouvellesReanimations":0,"deces":1062,"gueris":4066,"source":{"nom":"OpenCOVID19-fr"},"sourceType":"opencovid19-fr"},{"code":"REG-28","nom":"Normandie","date":"2020-08-06","hospitalises":126,"reanimation":4,"nouvellesHospitalisations":3,"nouvellesReanimations":0,"deces":442,"gueris":1807,"source":{"nom":"OpenCOVID19-fr"},"sourceType":"opencovid19-fr"},{"code":"REG-32","nom":"Hauts-de-France","date":"2020-08-06","hospitalises":484,"reanimation":41,"nouvellesHospitalisations":8,"nouvellesReanimations":1,"deces":1919,"gueris":7039,"source":{"nom":"OpenCOVID19-fr"},"sourceType":"opencovid19-fr"},{"code":"REG-44","nom":"Grand Est","date":"2020-08-06","hospitalises":569,"reanimation":16,"nouvellesHospitalisations":10,"nouvellesReanimations":1,"deces":3625,"gueris":12838,"source":{"nom":"OpenCOVID19-fr"},"sourceType":"opencovid19-fr"},{"code":"REG-52","nom":"Pays de la Loire","date":"2020-08-06","hospitalises":101,"reanimation":12,"nouvellesHospitalisations":14,"nouvellesReanimations":4,"deces":478,"gueris":2272,"source":{"nom":"OpenCOVID19-fr"},"sourceType":"opencovid19-fr"},{"code":"REG-53","nom":"Bretagne","date":"2020-08-06","hospitalises":60,"reanimation":7,"nouvellesHospitalisations":0,"nouvellesReanimations":1,"deces":267,"gueris":1346,"source":{"nom":"OpenCOVID19-fr"},"sourceType":"opencovid19-fr"},{"code":"REG-75","nom":"Nouvelle-Aquitaine","date":"2020-08-06","hospitalises":50,"reanimation":9,"nouvellesHospitalisations":2,"nouvellesReanimations":0,"deces":426,"gueris":2260,"source":{"nom":"OpenCOVID19-fr"},"sourceType":"opencovid19-fr"},{"code":"REG-76","nom":"Occitanie","date":"2020-08-06","hospitalises":49,"reanimation":12,"nouvellesHospitalisations":3,"nouvellesReanimations":1,"deces":515,"gueris":2973,"source":{"nom":"OpenCOVID19-fr"},"sourceType":"opencovid19-fr"},{"code":"REG-84","nom":"Auvergne-Rhône-Alpes","date":"2020-08-06","hospitalises":301,"reanimation":18,"nouvellesHospitalisations":7,"nouvellesReanimations":1,"deces":1761,"gueris":8098,"source":{"nom":"OpenCOVID19-fr"},"sourceType":"opencovid19-fr"},{"code":"REG-93","nom":"Provence-Alpes-Côte d'Azur","date":"2020-08-06","hospitalises":387,"reanimation":19,"nouvellesHospitalisations":7,"nouvellesReanimations":1,"deces":967,"gueris":5786,"source":{"nom":"OpenCOVID19-fr"},"sourceType":"opencovid19-fr"},{"code":"REG-94","nom":"Corse","date":"2020-08-06","hospitalises":7,"reanimation":0,"nouvellesHospitalisations":0,"nouvellesReanimations":0,"deces":59,"gueris":252,"source":{"nom":"OpenCOVID19-fr"},"sourceType":"opencovid19-fr"}]}