{"allFranceDataByDate":[{"code":"DEP-01","nom":"Ain","date":"2020-12-06","hospitalises":346,"reanimation":28,"nouvellesHospitalisations":4,"nouvellesReanimations":0,"deces":321,"gueris":1277,"source":{"nom":"Santé publique France Data"},"sourceType":"sante-publique-france-data"},{"code":"DEP-02","nom":"Aisne","date":"2020-12-06","hospitalises":216,"reanimation":22,"nouvellesHospitalisations":3,"nouvellesReanimations":0,"deces":406,"gueris":1736,"source":{"nom":"Santé publique France Data"},"sourceType":"sante-publique-france-data"},{"code":"DEP-03","nom":"Allier","date":"2020-12-06","hospitalises":232,"reanimation":19,"nouvellesHospitalisations":12,"nouvellesReanimations":0,"deces":237,"gueris":814,"source":{"nom":"Santé publique France Data"},"sourceType":"sante-publique-france-data"},{"code":"DEP-04","nom":"Alpes-de-Haute-Provence","date":"2020-12-06","hospitalises":129,"reanimation":5,"nouvellesHospitalisations":8,"nouvellesReanimations":0,"deces":81,"gueris":449,"source":{"nom":"Santé publique France Data"},"sourceType":"sante-publique-france-data"},{"code":"DEP-05","nom":"Hautes-Alpes","date":"2020-12-06","hospitalises":164,"reanimation":11,"nouvellesHospitalisations":3,"nouvellesReanimations":0,"deces":110,"gueris":492,"source":{"nom":"Santé publique France Data"},"sourceType":"sante-publique-france-data"},{"code":"DEP-06","nom":"Alpes-Maritimes","date":"2020-12-06","hospitalises":474,"reanimation":55,"nouvellesHospitalisations":16,"nouvellesReanimations":5,"deces":452,"gueris":2136,"source":{"nom":"Santé publique France Data"},"sourceType":"sante-publique-france-data"},{"code":"DEP-07","nom":"Ardèche","date":"2020-12-06","hospitalises":182,"reanimation":13,"nouvellesHospitalisations":4,"nouvellesReanimations":0,"deces":269,"gueris":940,"source":{"nom":"Santé publique France Data"},"sourceType":"sante-publique-france-data"},{"code":"DEP-08","nom":"Ardennes","date":"2020-12-06","hospitalises":175,"reanimation":14,"nouvellesHospitalisations":20,"nouvellesReanimations":0,"deces":160,"gueris":442,"source":{"nom":"Santé publique France Data"},"sourceType":"sante-publique-france-data"},{"code":"DEP-09","nom":"Ariège","date":"2020-12-06","hospitalises":35,"reanimation":2,"nouvellesHospitalisations":2,"nouvellesReanimations":0,"deces":24,"gueris":120,"source":{"nom":"Santé publique France Data"},"sourceType":"sante-publique-france-data"},{"code":"DEP-10","nom":"Aube","date":"2020-12-06","hospitalises":143,"reanimation":13,"nouvellesHospitalisations":3,"nouvellesReanimations":0,"deces":224,"gueris":957,"source":{"nom":"Santé publique France Data"},"sourceType":"sante-publique-france-data"},{"code":"DEP-11","nom":"Aude","date":"2020-12-06","hospitalises":64,"reanimation":5,"nouvellesHospitalisations":0,"nouvellesReanimations":0,"deces":116,"gueris":465,"source":{"nom":"Santé publique France Data"},"sourceType":"sante-publique-france-data"},{"code":"DEP-12","nom":"Aveyron","date":"2020-12-06","hospitalises":89,"reanimation":6,"nouvellesHospitalisations":2,"nouvellesReanimations":0,"deces":113,"gueris":405,"source":{"nom":"Santé publique France Data"},"sourceType":"sante-publique-france-data"},{"code":"DEP-13","nom":"Bouches-du-Rhône","date":"2020-12-06","hospitalises":1107,"reanimation":213,"nouvellesHospitalisations":28,"nouvellesReanimations":11,"deces":1525,"gueris":9754,"source":{"nom":"Santé publique France Data"},"sourceType":"sante-publique-france-data"},{"code":"DEP-14","nom":"Calvados","date":"2020-12-06","hospitalises":196,"reanimation":17,"nouvellesHospitalisations":4,"nouvellesReanimations":1,"deces":223,"gueris":932,"source":{"nom":"Santé publique France Data"},"sourceType":"sante-publique-france-data"},{"code":"DEP-15","nom":"Cantal","date":"2020-12-06","hospitalises":71,"reanimation":12,"nouvellesHospitalisations":2,"nouvellesReanimations":3,"deces":43,"gueris":218,"source":{"nom":"Santé publique France Data"},"sourceType":"sante-publique-france-data"},{"code":"DEP-16","nom":"Charente","date":"2020-12-06","hospitalises":38,"reanimation":2,"nouvellesHospitalisations":0,"nouvellesReanimations":0,"deces":35,"gueris":186,"source":{"nom":"Santé publique France Data"},"sourceType":"sante-publique-france-data"},{"code":"DEP-17","nom":"Charente-Maritime","date":"2020-12-06","hospitalises":64,"reanimation":12,"nouvellesHospitalisations":1,"nouvellesReanimations":0,"deces":106,"gueris":396,"source":{"nom":"Santé publique France Data"},"sourceType":"sante-publique-france-data"},{"code":"DEP-18","nom":"Cher","date":"2020-12-06","hospitalises":166,"reanimation":8,"nouvellesHospitalisations":9,"nouvellesReanimations":1,"deces":217,"gueris":516,"source":{"nom":"Santé publique France Data"},"sourceType":"sante-publique-france-data"},{"code":"DEP-19","nom":"Corrèze","date":"2020-12-06","hospitalises":32,"reanimation":4,"nouvellesHospitalisations":0,"nouvellesReanimations":0,"deces":83,"gueris":348,"source":{"nom":"Santé publique France Data"},"sourceType":"sante-publique-france-data"},{"code":"DEP-21","nom":"Côte-d'Or","date":"2020-12-06","hospitalises":325,"reanimation":51,"nouvellesHospitalisations":11,"nouvellesReanimations":2,"deces":418,"gueris":1708,"source":{"nom":"Santé publique France Data"},"sourceType":"sante-publique-france-data"},{"code":"DEP-22","nom":"Côtes-d'Armor","date":"2020-12-06","hospitalises":72,"reanimation":9,"nouvellesHospitalisations":7,"nouvellesReanimations":1,"deces":88,"gueris":469,"source":{"nom":"Santé publique France Data"},"sourceType":"sante-publique-france-data"},{"code":"DEP-23","nom":"Creuse","date":"2020-12-06","hospitalises":38,"reanimation":3,"nouvellesHospitalisations":1,"nouvellesReanimations":0,"deces":47,"gueris":247,"source":{"nom":"Santé publique France Data"},"sourceType":"sante-publique-france-data"},{"code":"DEP-24","nom":"Dordogne","date":"2020-12-06","hospitalises":77,"reanimation":7,"nouvellesHospitalisations":3,"nouvellesReanimations":0,"deces":39,"gueris":257,"source":{"nom":"Santé publique France Data"},"sourceType":"sante-publique-france-data"},{"code":"DEP-25","nom":"Doubs","date":"2020-12-06","hospitalises":182,"reanimation":56,"nouvellesHospitalisations":25,"nouvellesReanimations":8,"deces":242,"gueris":1099,"source":{"nom":"Santé publique France Data"},"sourceType":"sante-publique-france-data"},{"code":"DEP-26","nom":"Drôme","date":"2020-12-06","hospitalises":240,"reanimation":35,"nouvellesHospitalisations":12,"nouvellesReanimations":1,"deces":346,"gueris":1290,"source":{"nom":"Santé publique France Data"},"sourceType":"sante-publique-france-data"},{"code":"DEP-27","nom":"Eure","date":"2020-12-06","hospitalises":189,"reanimation":8,"nouvellesHospitalisations":2,"nouvellesReanimations":2,"deces":204,"gueris":681,"source":{"nom":"Santé publique France Data"},"sourceType":"sante-publique-france-data"},{"code":"DEP-28","nom":"Eure-et-Loir","date":"2020-12-06","hospitalises":188,"reanimation":21,"nouvellesHospitalisations":6,"nouvellesReanimations":0,"deces":224,"gueris":1124,"source":{"nom":"Santé publique France Data"},"sourceType":"sante-publique-france-data"},{"code":"DEP-29","nom":"Finistère","date":"2020-12-06","hospitalises":70,"reanimation":16,"nouvellesHospitalisations":2,"nouvellesReanimations":0,"deces":90,"gueris":457,"source":{"nom":"Santé publique France Data"},"sourceType":"sante-publique-france-data"},{"code":"DEP-2A","nom":"Corse-du-Sud","date":"2020-12-06","hospitalises":21,"reanimation":7,"nouvellesHospitalisations":0,"nouvellesReanimations":1,"deces":76,"gueris":263,"source":{"nom":"Santé publique France Data"},"sourceType":"sante-publique-france-data"},{"code":"DEP-2B","nom":"Haute-Corse","date":"2020-12-06","hospitalises":14,"reanimation":1,"nouvellesHospitalisations":0,"nouvellesReanimations":0,"deces":36,"gueris":218,"source":{"nom":"Santé publique France Data"},"sourceType":"sante-publique-france-data"},{"code":"DEP-30","nom":"Gard","date":"2020-12-06","hospitalises":239,"reanimation":38,"nouvellesHospitalisations":3,"nouvellesReanimations":0,"deces":283,"gueris":1215,"source":{"nom":"Santé publique France Data"},"sourceType":"sante-publique-france-data"},{"code":"DEP-31","nom":"Haute-Garonne","date":"2020-12-06","hospitalises":292,"reanimation":66,"nouvellesHospitalisations":1,"nouvellesReanimations":0,"deces":294,"gueris":2221,"source":{"nom":"Santé publique France Data"},"sourceType":"sante-publique-france-data"},{"code":"DEP-32","nom":"Gers","date":"2020-12-06","hospitalises":28,"reanimation":4,"nouvellesHospitalisations":1,"nouvellesReanimations":0,"deces":53,"gueris":163,"source":{"nom":"Santé publique France Data"},"sourceType":"sante-publique-france-data"},{"code":"DEP-33","nom":"Gironde","date":"2020-12-06","hospitalises":356,"reanimation":73,"nouvellesHospitalisations":16,"nouvellesReanimations":4,"deces":387,"gueris":2263,"source":{"nom":"Santé publique France Data"},"sourceType":"sante-publique-france-data"},{"code":"DEP-34","nom":"Hérault","date":"2020-12-06","hospitalises":272,"reanimation":54,"nouvellesHospitalisations":3,"nouvellesReanimations":1,"deces":423,"gueris":2131,"source":{"nom":"Santé publique France Data"},"sourceType":"sante-publique-france-data"},{"code":"DEP-35","nom":"Ille-et-Vilaine","date":"2020-12-06","hospitalises":261,"reanimation":31,"nouvellesHospitalisations":5,"nouvellesReanimations":1,"deces":226,"gueris":1164,"source":{"nom":"Santé publique France Data"},"sourceType":"sante-publique-france-data"},{"code":"DEP-36","nom":"Indre","date":"2020-12-06","hospitalises":69,"reanimation":5,"nouvellesHospitalisations":8,"nouvellesReanimations":0,"deces":124,"gueris":370,"source":{"nom":"Santé publique France Data"},"sourceType":"sante-publique-france-data"},{"code":"DEP-37","nom":"Indre-et-Loire","date":"2020-12-06","hospitalises":148,"reanimation":34,"nouvellesHospitalisations":2,"nouvellesReanimations":1,"deces":182,"gueris":787,"source":{"nom":"Santé publique France Data"},"sourceType":"sante-publique-france-data"},{"code":"DEP-38","nom":"Isère","date":"2020-12-06","hospitalises":829,"reanimation":80,"nouvellesHospitalisations":12,"nouvellesReanimations":3,"deces":767,"gueris":3171,"source":{"nom":"Santé publique France Data"},"sourceType":"sante-publique-france-data"},{"code":"DEP-39","nom":"Jura","date":"2020-12-06","hospitalises":187,"reanimation":11,"nouvellesHospitalisations":0,"nouvellesReanimations":0,"deces":168,"gueris":742,"source":{"nom":"Santé publique France Data"},"sourceType":"sante-publique-france-data"},{"code":"DEP-40","nom":"Landes","date":"2020-12-06","hospitalises":96,"reanimation":8,"nouvellesHospitalisations":0,"nouvellesReanimations":0,"deces":66,"gueris":303,"source":{"nom":"Santé publique France Data"},"sourceType":"sante-publique-france-data"},{"code":"DEP-41","nom":"Loir-et-Cher","date":"2020-12-06","hospitalises":132,"reanimation":3,"nouvellesHospitalisations":8,"nouvellesReanimations":0,"deces":127,"gueris":560,"source":{"nom":"Santé publique France Data"},"sourceType":"sante-publique-france-data"},{"code":"DEP-42","nom":"Loire","date":"2020-12-06","hospitalises":706,"reanimation":78,"nouvellesHospitalisations":5,"nouvellesReanimations":0,"deces":735,"gueris":2802,"source":{"nom":"Santé publique France Data"},"sourceType":"sante-publique-france-data"},{"code":"DEP-43","nom":"Haute-Loire","date":"2020-12-06","hospitalises":163,"reanimation":8,"nouvellesHospitalisations":4,"nouvellesReanimations":0,"deces":108,"gueris":563,"source":{"nom":"Santé publique France Data"},"sourceType":"sante-publique-france-data"},{"code":"DEP-44","nom":"Loire-Atlantique","date":"2020-12-06","hospitalises":256,"reanimation":30,"nouvellesHospitalisations":4,"nouvellesReanimations":1,"deces":362,"gueris":1631,"source":{"nom":"Santé publique France Data"},"sourceType":"sante-publique-france-data"},{"code":"DEP-45","nom":"Loiret","date":"2020-12-06","hospitalises":195,"reanimation":41,"nouvellesHospitalisations":6,"nouvellesReanimations":1,"deces":206,"gueris":1261,"source":{"nom":"Santé publique France Data"},"sourceType":"sante-publique-france-data"},{"code":"DEP-46","nom":"Lot","date":"2020-12-06","hospitalises":43,"reanimation":1,"nouvellesHospitalisations":0,"nouvellesReanimations":0,"deces":43,"gueris":133,"source":{"nom":"Santé publique France Data"},"sourceType":"sante-publique-france-data"},{"code":"DEP-47","nom":"Lot-et-Garonne","date":"2020-12-06","hospitalises":75,"reanimation":16,"nouvellesHospitalisations":3,"nouvellesReanimations":0,"deces":50,"gueris":299,"source":{"nom":"Santé publique France Data"},"sourceType":"sante-publique-france-data"},{"code":"DEP-48","nom":"Lozère","date":"2020-12-06","hospitalises":36,"reanimation":4,"nouvellesHospitalisations":1,"nouvellesReanimations":0,"deces":44,"gueris":140,"source":{"nom":"Santé publique France Data"},"sourceType":"sante-publique-france-data"},{"code":"DEP-49","nom":"Maine-et-Loire","date":"2020-12-06","hospitalises":221,"reanimation":31,"nouvellesHospitalisations":5,"nouvellesReanimations":1,"deces":310,"gueris":1448,"source":{"nom":"Santé publique France Data"},"sourceType":"sante-publique-france-data"},{"code":"DEP-50","nom":"Manche","date":"2020-12-06","hospitalises":121,"reanimation":10,"nouvellesHospitalisations":2,"nouvellesReanimations":0,"deces":120,"gueris":454,"source":{"nom":"Santé publique France Data"},"sourceType":"sante-publique-france-data"},{"code":"DEP-51","nom":"Marne","date":"2020-12-06","hospitalises":201,"reanimation":28,"nouvellesHospitalisations":7,"nouvellesReanimations":0,"deces":390,"gueris":1602,"source":{"nom":"Santé publique France Data"},"sourceType":"sante-publique-france-data"},{"code":"DEP-52","nom":"Haute-Marne","date":"2020-12-06","hospitalises":122,"reanimation":5,"nouvellesHospitalisations":4,"nouvellesReanimations":0,"deces":154,"gueris":474,"source":{"nom":"Santé publique France Data"},"sourceType":"sante-publique-france-data"},{"code":"DEP-53","nom":"Mayenne","date":"2020-12-06","hospitalises":96,"reanimation":7,"nouvellesHospitalisations":0,"nouvellesReanimations":0,"deces":112,"gueris":526,"source":{"nom":"Santé publique France Data"},"sourceType":"sante-publique-france-data"},{"code":"DEP-54","nom":"Meurthe-et-Moselle","date":"2020-12-06","hospitalises":361,"reanimation":53,"nouvellesHospitalisations":8,"nouvellesReanimations":1,"deces":528,"gueris":1977,"source":{"nom":"Santé publique France Data"},"sourceType":"sante-publique-france-data"},{"code":"DEP-55","nom":"Meuse","date":"2020-12-06","hospitalises":63,"reanimation":7,"nouvellesHospitalisations":5,"nouvellesReanimations":0,"deces":151,"gueris":680,"source":{"nom":"Santé publique France Data"},"sourceType":"sante-publique-france-data"},{"code":"DEP-56","nom":"Morbihan","date":"2020-12-06","hospitalises":128,"reanimation":13,"nouvellesHospitalisations":1,"nouvellesReanimations":0,"deces":181,"gueris":841,"source":{"nom":"Santé publique France Data"},"sourceType":"sante-publique-france-data"},{"code":"DEP-57","nom":"Moselle","date":"2020-12-06","hospitalises":463,"reanimation":54,"nouvellesHospitalisations":10,"nouvellesReanimations":4,"deces":1155,"gueris":3624,"source":{"nom":"Santé publique France Data"},"sourceType":"sante-publique-france-data"},{"code":"DEP-58","nom":"Nièvre","date":"2020-12-06","hospitalises":88,"reanimation":6,"nouvellesHospitalisations":2,"nouvellesReanimations":0,"deces":79,"gueris":282,"source":{"nom":"Santé publique France Data"},"sourceType":"sante-publique-france-data"},{"code":"DEP-59","nom":"Nord","date":"2020-12-06","hospitalises":1245,"reanimation":158,"nouvellesHospitalisations":9,"nouvellesReanimations":2,"deces":1624,"gueris":7070,"source":{"nom":"Santé publique France Data"},"sourceType":"sante-publique-france-data"},{"code":"DEP-60","nom":"Oise","date":"2020-12-06","hospitalises":279,"reanimation":26,"nouvellesHospitalisations":2,"nouvellesReanimations":0,"deces":569,"gueris":1915,"source":{"nom":"Santé publique France Data"},"sourceType":"sante-publique-france-data"},{"code":"DEP-61","nom":"Orne","date":"2020-12-06","hospitalises":150,"reanimation":9,"nouvellesHospitalisations":1,"nouvellesReanimations":1,"deces":118,"gueris":542,"source":{"nom":"Santé publique France Data"},"sourceType":"sante-publique-france-data"},{"code":"DEP-62","nom":"Pas-de-Calais","date":"2020-12-06","hospitalises":684,"reanimation":82,"nouvellesHospitalisations":19,"nouvellesReanimations":1,"deces":745,"gueris":3273,"source":{"nom":"Santé publique France Data"},"sourceType":"sante-publique-france-data"},{"code":"DEP-63","nom":"Puy-de-Dôme","date":"2020-12-06","hospitalises":279,"reanimation":23,"nouvellesHospitalisations":6,"nouvellesReanimations":2,"deces":279,"gueris":1013,"source":{"nom":"Santé publique France Data"},"sourceType":"sante-publique-france-data"},{"code":"DEP-64","nom":"Pyrénées-Atlantiques","date":"2020-12-06","hospitalises":252,"reanimation":19,"nouvellesHospitalisations":9,"nouvellesReanimations":2,"deces":215,"gueris":1041,"source":{"nom":"Santé publique France Data"},"sourceType":"sante-publique-france-data"},{"code":"DEP-65","nom":"Hautes-Pyrénées","date":"2020-12-06","hospitalises":137,"reanimation":11,"nouvellesHospitalisations":7,"nouvellesReanimations":1,"deces":97,"gueris":449,"source":{"nom":"Santé publique France Data"},"sourceType":"sante-publique-france-data"},{"code":"DEP-66","nom":"Pyrénées-Orientales","date":"2020-12-06","hospitalises":61,"reanimation":14,"nouvellesHospitalisations":0,"nouvellesReanimations":0,"deces":113,"gueris":571,"source":{"nom":"Santé publique France Data"},"sourceType":"sante-publique-france-data"},{"code":"DEP-67","nom":"Bas-Rhin","date":"2020-12-06","hospitalises":444,"reanimation":59,"nouvellesHospitalisations":5,"nouvellesReanimations":2,"deces":906,"gueris":3787,"source":{"nom":"Santé publique France Data"},"sourceType":"sante-publique-france-data"},{"code":"DEP-68","nom":"Haut-Rhin","date":"2020-12-06","hospitalises":327,"reanimation":37,"nouvellesHospitalisations":24,"nouvellesReanimations":1,"deces":932,"gueris":3785,"source":{"nom":"Santé publique France Data"},"sourceType":"sante-publique-france-data"},{"code":"DEP-69","nom":"Rhône","date":"2020-12-06","hospitalises":1375,"reanimation":172,"nouvellesHospitalisations":23,"nouvellesReanimations":6,"deces":1583,"gueris":7786,"source":{"nom":"Santé publique France Data"},"sourceType":"sante-publique-france-data"},{"code":"DEP-70","nom":"Haute-Saône","date":"2020-12-06","hospitalises":74,"reanimation":9,"nouvellesHospitalisations":0,"nouvellesReanimations":0,"deces":126,"gueris":536,"source":{"nom":"Santé publique France Data"},"sourceType":"sante-publique-france-data"},{"code":"DEP-71","nom":"Saône-et-Loire","date":"2020-12-06","hospitalises":465,"reanimation":40,"nouvellesHospitalisations":10,"nouvellesReanimations":2,"deces":540,"gueris":1915,"source":{"nom":"Santé publique France Data"},"sourceType":"sante-publique-france-data"},{"code":"DEP-72","nom":"Sarthe","date":"2020-12-06","hospitalises":258,"reanimation":11,"nouvellesHospitalisations":4,"nouvellesReanimations":0,"deces":174,"gueris":957,"source":{"nom":"Santé publique France Data"},"sourceType":"sante-publique-france-data"},{"code":"DEP-73","nom":"Savoie","date":"2020-12-06","hospitalises":265,"reanimation":26,"nouvellesHospitalisations":5,"nouvellesReanimations":1,"deces":390,"gueris":1456,"source":{"nom":"Santé publique France Data"},"sourceType":"sante-publique-france-data"},{"code":"DEP-74","nom":"Haute-Savoie","date":"2020-12-06","hospitalises":451,"reanimation":54,"nouvellesHospitalisations":18,"nouvellesReanimations":3,"deces":530,"gueris":2492,"source":{"nom":"Santé publique France Data"},"sourceType":"sante-publique-france-data"},{"code":"DEP-75","nom":"Paris","date":"2020-12-06","hospitalises":883,"reanimation":169,"nouvellesHospitalisations":16,"nouvellesReanimations":3,"deces":2529,"gueris":10320,"source":{"nom":"Santé publique France Data"},"sourceType":"sante-publique-france-data"},{"code":"DEP-76","nom":"Seine-Maritime","date":"2020-12-06","hospitalises":489,"reanimation":54,"nouvellesHospitalisations":7,"nouvellesReanimations":2,"deces":573,"gueris":2226,"source":{"nom":"Santé publique France Data"},"sourceType":"sante-publique-france-data"},{"code":"DEP-77","nom":"Seine-et-Marne","date":"2020-12-06","hospitalises":417,"reanimation":76,"nouvellesHospitalisations":18,"nouvellesReanimations":1,"deces":1059,"gueris":4573,"source":{"nom":"Santé publique France Data"},"sourceType":"sante-publique-france-data"},{"code":"DEP-78","nom":"Yvelines","date":"2020-12-06","hospitalises":788,"reanimation":60,"nouvellesHospitalisations":2,"nouvellesReanimations":0,"deces":916,"gueris":4081,"source":{"nom":"Santé publique France Data"},"sourceType":"sante-publique-france-data"},{"code":"DEP-79","nom":"Deux-Sèvres","date":"2020-12-06","hospitalises":86,"reanimation":8,"nouvellesHospitalisations":12,"nouvellesReanimations":2,"deces":80,"gueris":246,"source":{"nom":"Santé publique France Data"},"sourceType":"sante-publique-france-data"},{"code":"DEP-80","nom":"Somme","date":"2020-12-06","hospitalises":197,"reanimation":33,"nouvellesHospitalisations":3,"nouvellesReanimations":0,"deces":344,"gueris":1181,"source":{"nom":"Santé publique France Data"},"sourceType":"sante-publique-france-data"},{"code":"DEP-81","nom":"Tarn","date":"2020-12-06","hospitalises":146,"reanimation":21,"nouvellesHospitalisations":5,"nouvellesReanimations":1,"deces":110,"gueris":472,"source":{"nom":"Santé publique France Data"},"sourceType":"sante-publique-france-data"},{"code":"DEP-82","nom":"Tarn-et-Garonne","date":"2020-12-06","hospitalises":66,"reanimation":7,"nouvellesHospitalisations":1,"nouvellesReanimations":1,"deces":79,"gueris":360,"source":{"nom":"Santé publique France Data"},"sourceType":"sante-publique-france-data"},{"code":"DEP-83","nom":"Var","date":"2020-12-06","hospitalises":271,"reanimation":47,"nouvellesHospitalisations":7,"nouvellesReanimations":2,"deces":413,"gueris":2206,"source":{"nom":"Santé publique France Data"},"sourceType":"sante-publique-france-data"},{"code":"DEP-84","nom":"Vaucluse","date":"2020-12-06","hospitalises":293,"reanimation":19,"nouvellesHospitalisations":20,"nouvellesReanimations":0,"deces":355,"gueris":1398,"source":{"nom":"Santé publique France Data"},"sourceType":"sante-publique-france-data"},{"code":"DEP-85","nom":"Vendée","date":"2020-12-06","hospitalises":81,"reanimation":9,"nouvellesHospitalisations":0,"nouvellesReanimations":0,"deces":96,"gueris":604,"source":{"nom":"Santé publique France Data"},"sourceType":"sante-publique-france-data"},{"code":"DEP-86","nom":"Vienne","date":"2020-12-06","hospitalises":57,"reanimation":16,"nouvellesHospitalisations":5,"nouvellesReanimations":5,"deces":120,"gueris":467,"source":{"nom":"Santé publique France Data"},"sourceType":"sante-publique-france-data"},{"code":"DEP-87","nom":"Haute-Vienne","date":"2020-12-06","hospitalises":160,"reanimation":7,"nouvellesHospitalisations":0,"nouvellesReanimations":0,"deces":124,"gueris":431,"source":{"nom":"Santé publique France Data"},"sourceType":"sante-publique-france-data"},{"code":"DEP-88","nom":"Vosges","date":"2020-12-06","hospitalises":237,"reanimation":12,"nouvellesHospitalisations":15,"nouvellesReanimations":0,"deces":392,"gueris":1180,"source":{"nom":"Santé publique France Data"},"sourceType":"sante-publique-france-data"},{"code":"DEP-89","nom":"Yonne","date":"2020-12-06","hospitalises":226,"reanimation":17,"nouvellesHospitalisations":2,"nouvellesReanimations":0,"deces":181,"gueris":840,"source":{"nom":"Santé publique France Data"},"sourceType":"sante-publique-france-data"},{"code":"DEP-90","nom":"Territoire de Belfort","date":"2020-12-06","hospitalises":158,"reanimation":20,"nouvellesHospitalisations":1,"nouvellesReanimations":0,"deces":289,"gueris":847,"source":{"nom":"Santé publique France Data"},"sourceType":"sante-publique-france-data"},{"code":"DEP-91","nom":"Essonne","date":"2020-12-06","hospitalises":583,"reanimation":78,"nouvellesHospitalisations":8,"nouvellesReanimations":0,"deces":928,"gueris":4585,"source":{"nom":"Santé publique France Data"},"sourceType":"sante-publique-france-data"},{"code":"DEP-92","nom":"Hauts-de-Seine","date":"2020-12-06","hospitalises":709,"reanimation":112,"nouvellesHospitalisations":18,"nouvellesReanimations":3,"deces":1484,"gueris":7725,"source":{"nom":"Santé publique France Data"},"sourceType":"sante-publique-france-data"},{"code":"DEP-93","nom":"Seine-Saint-Denis","date":"2020-12-06","hospitalises":683,"reanimation":81,"nouvellesHospitalisations":8,"nouvellesReanimations":1,"deces":1416,"gueris":6981,"source":{"nom":"Santé publique France Data"},"sourceType":"sante-publique-france-data"},{"code":"DEP-94","nom":"Val-de-Marne","date":"2020-12-06","hospitalises":777,"reanimation":68,"nouvellesHospitalisations":8,"nouvellesReanimations":1,"deces":1724,"gueris":7272,"source":{"nom":"Santé publique France Data"},"sourceType":"sante-publique-france-data"},{"code":"DEP-95","nom":"Val-d'Oise","date":"2020-12-06","hospitalises":434,"reanimation":44,"nouvellesHospitalisations":6,"nouvellesReanimations":1,"deces":1076,"gueris":4624,"source":{"nom":"Santé publique France Data"},"sourceType":"sante-publique-france-data"},{"code":"DEP-971","nom":"Guadeloupe","date":"2020-12-06","hospitalises":81,"reanimation":6,"nouvellesHospitalisations":0,"nouvellesReanimations":0,"deces":165,"gueris":722,"source":{"nom":"Santé publique France Data"},"sourceType":"sante-publique-france-data"},{"code":"DEP-972","nom":"Martinique","date":"2020-12-06","hospitalises":31,"reanimation":10,"nouvellesHospitalisations":0,"nouvellesReanimations":0,"deces":41,"gueris":342,"source":{"nom":"Santé publique France Data"},"sourceType":"sante-publique-france-data"},{"code":"DEP-973","nom":"Guyane","date":"2020-12-06","hospitalises":18,"reanimation":0,"nouvellesHospitalisations":4,"nouvellesReanimations":0,"deces":67,"gueris":1883,"source":{"nom":"Santé publique France Data"},"sourceType":"sante-publique-france-data"},{"code":"DEP-974","nom":"La Réunion","date":"2020-12-06","hospitalises":52,"reanimation":8,"nouvellesHospitalisations":3,"nouvellesReanimations":0,"deces":50,"gueris":658,"source":{"nom":"Santé publique France Data"},"sourceType":"sante-publique-france-data"},{"code":"DEP-976","nom":"Mayotte","date":"2020-12-06","hospitalises":7,"reanimation":4,"nouvellesHospitalisations":0,"nouvellesReanimations":0,"deces":35,"gueris":520,"source":{"nom":"Santé publique France Data"},"sourceType":"sante-publique-france-data"},{"date":"2020-12-06","source":{"nom":"Ministère des Solidarités et de la Santé"},"sourceType":"ministere-sante","casConfirmes":2292497,"deces":37996,"decesEhpad":17159,"hospitalises":26293,"reanimation":3220,"gueris":169586,"casConfirmesEhpad":123298,"nouvellesHospitalisations":625,"nouvellesReanimations":101,"nom":"France","code":"FRA"},{"code":"FRA","nom":"France","date":"2020-12-06","hospitalises":26262,"reanimation":3210,"nouvellesHospitalisations":627,"nouvellesReanimations":101,"deces":37970,"gueris":169555,"source":{"nom":"OpenCOVID19-fr"},"sourceType":"opencovid19-fr"},{"code":"REG-01","nom":"Guadeloupe","date":"2020-12-06","hospitalises":81,"reanimation":6,"nouvellesHospitalisations":0,"nouvellesReanimations":0,"deces":165,"gueris":722,"source":{"nom":"OpenCOVID19-fr"},"sourceType":"opencovid19-fr"},{"code":"REG-02","nom":"Martinique","date":"2020-12-06","hospitalises":31,"reanimation":10,"nouvellesHospitalisations":0,"nouvellesReanimations":0,"deces":41,"gueris":342,"source":{"nom":"OpenCOVID19-fr"},"sourceType":"opencovid19-fr"},{"code":"REG-03","nom":"Guyane","date":"2020-12-06","hospitalises":18,"reanimation":0,"nouvellesHospitalisations":4,"nouvellesReanimations":0,"deces":67,"gueris":1883,"source":{"nom":"OpenCOVID19-fr"},"sourceType":"opencovid19-fr"},{"code":"REG-04","nom":"La Réunion","date":"2020-12-06","hospitalises":52,"reanimation":8,"nouvellesHospitalisations":3,"nouvellesReanimations":0,"deces":50,"gueris":658,"source":{"nom":"OpenCOVID19-fr"},"sourceType":"opencovid19-fr"},{"code":"REG-06","nom":"Mayotte","date":"2020-12-06","hospitalises":7,"reanimation":4,"nouvellesHospitalisations":0,"nouvellesReanimations":0,"deces":35,"gueris":520,"source":{"nom":"OpenCOVID19-fr"},"sourceType":"opencovid19-fr"},{"code":"REG-11","nom":"Île-de-France","date":"2020-12-06","hospitalises":5274,"reanimation":688,"nouvellesHospitalisations":84,"nouvellesReanimations":10,"deces":11132,"gueris":50161,"source":{"nom":"OpenCOVID19-fr"},"sourceType":"opencovid19-fr"},{"code":"REG-24","nom":"Centre-Val de Loire","date":"2020-12-06","hospitalises":898,"reanimation":112,"nouvellesHospitalisations":39,"nouvellesReanimations":3,"deces":1080,"gueris":4618,"source":{"nom":"OpenCOVID19-fr"},"sourceType":"opencovid19-fr"},{"code":"REG-27","nom":"Bourgogne-Franche-Comté","date":"2020-12-06","hospitalises":1705,"reanimation":210,"nouvellesHospitalisations":51,"nouvellesReanimations":12,"deces":2043,"gueris":7969,"source":{"nom":"OpenCOVID19-fr"},"sourceType":"opencovid19-fr"},{"code":"REG-28","nom":"Normandie","date":"2020-12-06","hospitalises":1145,"reanimation":98,"nouvellesHospitalisations":16,"nouvellesReanimations":6,"deces":1238,"gueris":4835,"source":{"nom":"OpenCOVID19-fr"},"sourceType":"opencovid19-fr"},{"code":"REG-32","nom":"Hauts-de-France","date":"2020-12-06","hospitalises":2621,"reanimation":321,"nouvellesHospitalisations":36,"nouvellesReanimations":3,"deces":3688,"gueris":15175,"source":{"nom":"OpenCOVID19-fr"},"sourceType":"opencovid19-fr"},{"code":"REG-44","nom":"Grand Est","date":"2020-12-06","hospitalises":2536,"reanimation":282,"nouvellesHospitalisations":101,"nouvellesReanimations":8,"deces":4992,"gueris":18508,"source":{"nom":"OpenCOVID19-fr"},"sourceType":"opencovid19-fr"},{"code":"REG-52","nom":"Pays de la Loire","date":"2020-12-06","hospitalises":912,"reanimation":88,"nouvellesHospitalisations":13,"nouvellesReanimations":2,"deces":1054,"gueris":5166,"source":{"nom":"OpenCOVID19-fr"},"sourceType":"opencovid19-fr"},{"code":"REG-53","nom":"Bretagne","date":"2020-12-06","hospitalises":531,"reanimation":69,"nouvellesHospitalisations":15,"nouvellesReanimations":2,"deces":585,"gueris":2931,"source":{"nom":"OpenCOVID19-fr"},"sourceType":"opencovid19-fr"},{"code":"REG-75","nom":"Nouvelle-Aquitaine","date":"2020-12-06","hospitalises":1331,"reanimation":175,"nouvellesHospitalisations":50,"nouvellesReanimations":13,"deces":1352,"gueris":6484,"source":{"nom":"OpenCOVID19-fr"},"sourceType":"opencovid19-fr"},{"code":"REG-76","nom":"Occitanie","date":"2020-12-06","hospitalises":1508,"reanimation":233,"nouvellesHospitalisations":26,"nouvellesReanimations":4,"deces":1792,"gueris":8845,"source":{"nom":"OpenCOVID19-fr"},"sourceType":"opencovid19-fr"},{"code":"REG-84","nom":"Auvergne-Rhône-Alpes","date":"2020-12-06","hospitalises":5139,"reanimation":548,"nouvellesHospitalisations":107,"nouvellesReanimations":19,"deces":5608,"gueris":23822,"source":{"nom":"OpenCOVID19-fr"},"sourceType":"opencovid19-fr"},{"code":"REG-93","nom":"Provence-Alpes-Côte d'Azur","date":"2020-12-06","hospitalises":2438,"reanimation":350,"nouvellesHospitalisations":82,"nouvellesReanimations":18,"deces":2936,"gueris":16435,"source":{"nom":"OpenCOVID19-fr"},"sourceType":"opencovid19-fr"},{"code":"REG-94","nom":"Corse","date":"2020-12-06","hospitalises":35,"reanimation":8,"nouvellesHospitalisations":0,"nouvellesReanimations":1,"deces":112,"gueris":481,"source":{"nom":"OpenCOVID19-fr"},"sourceType":"opencovid19-fr"}]}