{"allFranceDataByDate":[{"code":"DEP-01","nom":"Ain","date":"2020-12-12","hospitalises":331,"reanimation":27,"nouvellesHospitalisations":3,"nouvellesReanimations":1,"deces":340,"gueris":1336,"source":{"nom":"Santé publique France Data"},"sourceType":"sante-publique-france-data"},{"code":"DEP-02","nom":"Aisne","date":"2020-12-12","hospitalises":228,"reanimation":25,"nouvellesHospitalisations":26,"nouvellesReanimations":2,"deces":435,"gueris":1815,"source":{"nom":"Santé publique France Data"},"sourceType":"sante-publique-france-data"},{"code":"DEP-03","nom":"Allier","date":"2020-12-12","hospitalises":253,"reanimation":21,"nouvellesHospitalisations":9,"nouvellesReanimations":1,"deces":250,"gueris":863,"source":{"nom":"Santé publique France Data"},"sourceType":"sante-publique-france-data"},{"code":"DEP-04","nom":"Alpes-de-Haute-Provence","date":"2020-12-12","hospitalises":115,"reanimation":5,"nouvellesHospitalisations":0,"nouvellesReanimations":0,"deces":86,"gueris":475,"source":{"nom":"Santé publique France Data"},"sourceType":"sante-publique-france-data"},{"code":"DEP-05","nom":"Hautes-Alpes","date":"2020-12-12","hospitalises":145,"reanimation":11,"nouvellesHospitalisations":3,"nouvellesReanimations":3,"deces":120,"gueris":522,"source":{"nom":"Santé publique France Data"},"sourceType":"sante-publique-france-data"},{"code":"DEP-06","nom":"Alpes-Maritimes","date":"2020-12-12","hospitalises":493,"reanimation":57,"nouvellesHospitalisations":26,"nouvellesReanimations":3,"deces":477,"gueris":2237,"source":{"nom":"Santé publique France Data"},"sourceType":"sante-publique-france-data"},{"code":"DEP-07","nom":"Ardèche","date":"2020-12-12","hospitalises":160,"reanimation":12,"nouvellesHospitalisations":8,"nouvellesReanimations":1,"deces":276,"gueris":1007,"source":{"nom":"Santé publique France Data"},"sourceType":"sante-publique-france-data"},{"code":"DEP-08","nom":"Ardennes","date":"2020-12-12","hospitalises":178,"reanimation":12,"nouvellesHospitalisations":9,"nouvellesReanimations":0,"deces":172,"gueris":474,"source":{"nom":"Santé publique France Data"},"sourceType":"sante-publique-france-data"},{"code":"DEP-09","nom":"Ariège","date":"2020-12-12","hospitalises":30,"reanimation":1,"nouvellesHospitalisations":2,"nouvellesReanimations":0,"deces":26,"gueris":127,"source":{"nom":"Santé publique France Data"},"sourceType":"sante-publique-france-data"},{"code":"DEP-10","nom":"Aube","date":"2020-12-12","hospitalises":107,"reanimation":13,"nouvellesHospitalisations":6,"nouvellesReanimations":2,"deces":232,"gueris":1013,"source":{"nom":"Santé publique France Data"},"sourceType":"sante-publique-france-data"},{"code":"DEP-11","nom":"Aude","date":"2020-12-12","hospitalises":59,"reanimation":3,"nouvellesHospitalisations":9,"nouvellesReanimations":0,"deces":122,"gueris":478,"source":{"nom":"Santé publique France Data"},"sourceType":"sante-publique-france-data"},{"code":"DEP-12","nom":"Aveyron","date":"2020-12-12","hospitalises":87,"reanimation":4,"nouvellesHospitalisations":1,"nouvellesReanimations":0,"deces":116,"gueris":414,"source":{"nom":"Santé publique France Data"},"sourceType":"sante-publique-france-data"},{"code":"DEP-13","nom":"Bouches-du-Rhône","date":"2020-12-12","hospitalises":1012,"reanimation":176,"nouvellesHospitalisations":43,"nouvellesReanimations":7,"deces":1591,"gueris":10071,"source":{"nom":"Santé publique France Data"},"sourceType":"sante-publique-france-data"},{"code":"DEP-14","nom":"Calvados","date":"2020-12-12","hospitalises":167,"reanimation":15,"nouvellesHospitalisations":6,"nouvellesReanimations":0,"deces":233,"gueris":988,"source":{"nom":"Santé publique France Data"},"sourceType":"sante-publique-france-data"},{"code":"DEP-15","nom":"Cantal","date":"2020-12-12","hospitalises":64,"reanimation":12,"nouvellesHospitalisations":3,"nouvellesReanimations":1,"deces":47,"gueris":239,"source":{"nom":"Santé publique France Data"},"sourceType":"sante-publique-france-data"},{"code":"DEP-16","nom":"Charente","date":"2020-12-12","hospitalises":45,"reanimation":2,"nouvellesHospitalisations":3,"nouvellesReanimations":0,"deces":39,"gueris":199,"source":{"nom":"Santé publique France Data"},"sourceType":"sante-publique-france-data"},{"code":"DEP-17","nom":"Charente-Maritime","date":"2020-12-12","hospitalises":53,"reanimation":6,"nouvellesHospitalisations":1,"nouvellesReanimations":0,"deces":107,"gueris":410,"source":{"nom":"Santé publique France Data"},"sourceType":"sante-publique-france-data"},{"code":"DEP-18","nom":"Cher","date":"2020-12-12","hospitalises":179,"reanimation":7,"nouvellesHospitalisations":13,"nouvellesReanimations":0,"deces":234,"gueris":564,"source":{"nom":"Santé publique France Data"},"sourceType":"sante-publique-france-data"},{"code":"DEP-19","nom":"Corrèze","date":"2020-12-12","hospitalises":28,"reanimation":6,"nouvellesHospitalisations":1,"nouvellesReanimations":0,"deces":84,"gueris":361,"source":{"nom":"Santé publique France Data"},"sourceType":"sante-publique-france-data"},{"code":"DEP-21","nom":"Côte-d'Or","date":"2020-12-12","hospitalises":347,"reanimation":37,"nouvellesHospitalisations":18,"nouvellesReanimations":2,"deces":450,"gueris":1798,"source":{"nom":"Santé publique France Data"},"sourceType":"sante-publique-france-data"},{"code":"DEP-22","nom":"Côtes-d'Armor","date":"2020-12-12","hospitalises":85,"reanimation":7,"nouvellesHospitalisations":8,"nouvellesReanimations":0,"deces":90,"gueris":488,"source":{"nom":"Santé publique France Data"},"sourceType":"sante-publique-france-data"},{"code":"DEP-23","nom":"Creuse","date":"2020-12-12","hospitalises":30,"reanimation":3,"nouvellesHospitalisations":4,"nouvellesReanimations":0,"deces":48,"gueris":263,"source":{"nom":"Santé publique France Data"},"sourceType":"sante-publique-france-data"},{"code":"DEP-24","nom":"Dordogne","date":"2020-12-12","hospitalises":68,"reanimation":7,"nouvellesHospitalisations":2,"nouvellesReanimations":0,"deces":43,"gueris":280,"source":{"nom":"Santé publique France Data"},"sourceType":"sante-publique-france-data"},{"code":"DEP-25","nom":"Doubs","date":"2020-12-12","hospitalises":159,"reanimation":45,"nouvellesHospitalisations":8,"nouvellesReanimations":6,"deces":261,"gueris":1156,"source":{"nom":"Santé publique France Data"},"sourceType":"sante-publique-france-data"},{"code":"DEP-26","nom":"Drôme","date":"2020-12-12","hospitalises":223,"reanimation":35,"nouvellesHospitalisations":4,"nouvellesReanimations":0,"deces":359,"gueris":1360,"source":{"nom":"Santé publique France Data"},"sourceType":"sante-publique-france-data"},{"code":"DEP-27","nom":"Eure","date":"2020-12-12","hospitalises":164,"reanimation":5,"nouvellesHospitalisations":0,"nouvellesReanimations":0,"deces":213,"gueris":730,"source":{"nom":"Santé publique France Data"},"sourceType":"sante-publique-france-data"},{"code":"DEP-28","nom":"Eure-et-Loir","date":"2020-12-12","hospitalises":163,"reanimation":15,"nouvellesHospitalisations":11,"nouvellesReanimations":1,"deces":231,"gueris":1184,"source":{"nom":"Santé publique France Data"},"sourceType":"sante-publique-france-data"},{"code":"DEP-29","nom":"Finistère","date":"2020-12-12","hospitalises":83,"reanimation":12,"nouvellesHospitalisations":2,"nouvellesReanimations":0,"deces":93,"gueris":470,"source":{"nom":"Santé publique France Data"},"sourceType":"sante-publique-france-data"},{"code":"DEP-2A","nom":"Corse-du-Sud","date":"2020-12-12","hospitalises":17,"reanimation":5,"nouvellesHospitalisations":0,"nouvellesReanimations":0,"deces":77,"gueris":268,"source":{"nom":"Santé publique France Data"},"sourceType":"sante-publique-france-data"},{"code":"DEP-2B","nom":"Haute-Corse","date":"2020-12-12","hospitalises":12,"reanimation":1,"nouvellesHospitalisations":0,"nouvellesReanimations":0,"deces":36,"gueris":219,"source":{"nom":"Santé publique France Data"},"sourceType":"sante-publique-france-data"},{"code":"DEP-30","nom":"Gard","date":"2020-12-12","hospitalises":219,"reanimation":33,"nouvellesHospitalisations":7,"nouvellesReanimations":2,"deces":304,"gueris":1260,"source":{"nom":"Santé publique France Data"},"sourceType":"sante-publique-france-data"},{"code":"DEP-31","nom":"Haute-Garonne","date":"2020-12-12","hospitalises":312,"reanimation":69,"nouvellesHospitalisations":15,"nouvellesReanimations":0,"deces":303,"gueris":2300,"source":{"nom":"Santé publique France Data"},"sourceType":"sante-publique-france-data"},{"code":"DEP-32","nom":"Gers","date":"2020-12-12","hospitalises":30,"reanimation":3,"nouvellesHospitalisations":1,"nouvellesReanimations":0,"deces":54,"gueris":170,"source":{"nom":"Santé publique France Data"},"sourceType":"sante-publique-france-data"},{"code":"DEP-33","nom":"Gironde","date":"2020-12-12","hospitalises":379,"reanimation":72,"nouvellesHospitalisations":17,"nouvellesReanimations":2,"deces":411,"gueris":2347,"source":{"nom":"Santé publique France Data"},"sourceType":"sante-publique-france-data"},{"code":"DEP-34","nom":"Hérault","date":"2020-12-12","hospitalises":211,"reanimation":43,"nouvellesHospitalisations":2,"nouvellesReanimations":2,"deces":442,"gueris":2226,"source":{"nom":"Santé publique France Data"},"sourceType":"sante-publique-france-data"},{"code":"DEP-35","nom":"Ille-et-Vilaine","date":"2020-12-12","hospitalises":249,"reanimation":27,"nouvellesHospitalisations":7,"nouvellesReanimations":1,"deces":236,"gueris":1210,"source":{"nom":"Santé publique France Data"},"sourceType":"sante-publique-france-data"},{"code":"DEP-36","nom":"Indre","date":"2020-12-12","hospitalises":71,"reanimation":7,"nouvellesHospitalisations":5,"nouvellesReanimations":1,"deces":126,"gueris":393,"source":{"nom":"Santé publique France Data"},"sourceType":"sante-publique-france-data"},{"code":"DEP-37","nom":"Indre-et-Loire","date":"2020-12-12","hospitalises":165,"reanimation":34,"nouvellesHospitalisations":3,"nouvellesReanimations":0,"deces":195,"gueris":821,"source":{"nom":"Santé publique France Data"},"sourceType":"sante-publique-france-data"},{"code":"DEP-38","nom":"Isère","date":"2020-12-12","hospitalises":779,"reanimation":72,"nouvellesHospitalisations":44,"nouvellesReanimations":7,"deces":822,"gueris":3358,"source":{"nom":"Santé publique France Data"},"sourceType":"sante-publique-france-data"},{"code":"DEP-39","nom":"Jura","date":"2020-12-12","hospitalises":196,"reanimation":7,"nouvellesHospitalisations":7,"nouvellesReanimations":0,"deces":181,"gueris":794,"source":{"nom":"Santé publique France Data"},"sourceType":"sante-publique-france-data"},{"code":"DEP-40","nom":"Landes","date":"2020-12-12","hospitalises":121,"reanimation":8,"nouvellesHospitalisations":2,"nouvellesReanimations":0,"deces":75,"gueris":319,"source":{"nom":"Santé publique France Data"},"sourceType":"sante-publique-france-data"},{"code":"DEP-41","nom":"Loir-et-Cher","date":"2020-12-12","hospitalises":147,"reanimation":5,"nouvellesHospitalisations":7,"nouvellesReanimations":1,"deces":144,"gueris":593,"source":{"nom":"Santé publique France Data"},"sourceType":"sante-publique-france-data"},{"code":"DEP-42","nom":"Loire","date":"2020-12-12","hospitalises":600,"reanimation":67,"nouvellesHospitalisations":8,"nouvellesReanimations":2,"deces":776,"gueris":2929,"source":{"nom":"Santé publique France Data"},"sourceType":"sante-publique-france-data"},{"code":"DEP-43","nom":"Haute-Loire","date":"2020-12-12","hospitalises":127,"reanimation":7,"nouvellesHospitalisations":1,"nouvellesReanimations":0,"deces":129,"gueris":620,"source":{"nom":"Santé publique France Data"},"sourceType":"sante-publique-france-data"},{"code":"DEP-44","nom":"Loire-Atlantique","date":"2020-12-12","hospitalises":260,"reanimation":28,"nouvellesHospitalisations":19,"nouvellesReanimations":1,"deces":371,"gueris":1693,"source":{"nom":"Santé publique France Data"},"sourceType":"sante-publique-france-data"},{"code":"DEP-45","nom":"Loiret","date":"2020-12-12","hospitalises":176,"reanimation":33,"nouvellesHospitalisations":1,"nouvellesReanimations":0,"deces":222,"gueris":1311,"source":{"nom":"Santé publique France Data"},"sourceType":"sante-publique-france-data"},{"code":"DEP-46","nom":"Lot","date":"2020-12-12","hospitalises":39,"reanimation":2,"nouvellesHospitalisations":0,"nouvellesReanimations":1,"deces":47,"gueris":144,"source":{"nom":"Santé publique France Data"},"sourceType":"sante-publique-france-data"},{"code":"DEP-47","nom":"Lot-et-Garonne","date":"2020-12-12","hospitalises":54,"reanimation":7,"nouvellesHospitalisations":1,"nouvellesReanimations":0,"deces":61,"gueris":345,"source":{"nom":"Santé publique France Data"},"sourceType":"sante-publique-france-data"},{"code":"DEP-48","nom":"Lozère","date":"2020-12-12","hospitalises":23,"reanimation":3,"nouvellesHospitalisations":0,"nouvellesReanimations":0,"deces":48,"gueris":153,"source":{"nom":"Santé publique France Data"},"sourceType":"sante-publique-france-data"},{"code":"DEP-49","nom":"Maine-et-Loire","date":"2020-12-12","hospitalises":192,"reanimation":32,"nouvellesHospitalisations":8,"nouvellesReanimations":1,"deces":325,"gueris":1528,"source":{"nom":"Santé publique France Data"},"sourceType":"sante-publique-france-data"},{"code":"DEP-50","nom":"Manche","date":"2020-12-12","hospitalises":95,"reanimation":9,"nouvellesHospitalisations":5,"nouvellesReanimations":1,"deces":126,"gueris":503,"source":{"nom":"Santé publique France Data"},"sourceType":"sante-publique-france-data"},{"code":"DEP-51","nom":"Marne","date":"2020-12-12","hospitalises":191,"reanimation":24,"nouvellesHospitalisations":7,"nouvellesReanimations":0,"deces":398,"gueris":1656,"source":{"nom":"Santé publique France Data"},"sourceType":"sante-publique-france-data"},{"code":"DEP-52","nom":"Haute-Marne","date":"2020-12-12","hospitalises":135,"reanimation":0,"nouvellesHospitalisations":13,"nouvellesReanimations":1,"deces":164,"gueris":504,"source":{"nom":"Santé publique France Data"},"sourceType":"sante-publique-france-data"},{"code":"DEP-53","nom":"Mayenne","date":"2020-12-12","hospitalises":94,"reanimation":5,"nouvellesHospitalisations":2,"nouvellesReanimations":0,"deces":126,"gueris":559,"source":{"nom":"Santé publique France Data"},"sourceType":"sante-publique-france-data"},{"code":"DEP-54","nom":"Meurthe-et-Moselle","date":"2020-12-12","hospitalises":364,"reanimation":54,"nouvellesHospitalisations":15,"nouvellesReanimations":3,"deces":560,"gueris":2054,"source":{"nom":"Santé publique France Data"},"sourceType":"sante-publique-france-data"},{"code":"DEP-55","nom":"Meuse","date":"2020-12-12","hospitalises":79,"reanimation":9,"nouvellesHospitalisations":0,"nouvellesReanimations":0,"deces":158,"gueris":697,"source":{"nom":"Santé publique France Data"},"sourceType":"sante-publique-france-data"},{"code":"DEP-56","nom":"Morbihan","date":"2020-12-12","hospitalises":152,"reanimation":11,"nouvellesHospitalisations":10,"nouvellesReanimations":0,"deces":187,"gueris":865,"source":{"nom":"Santé publique France Data"},"sourceType":"sante-publique-france-data"},{"code":"DEP-57","nom":"Moselle","date":"2020-12-12","hospitalises":454,"reanimation":57,"nouvellesHospitalisations":18,"nouvellesReanimations":2,"deces":1208,"gueris":3764,"source":{"nom":"Santé publique France Data"},"sourceType":"sante-publique-france-data"},{"code":"DEP-58","nom":"Nièvre","date":"2020-12-12","hospitalises":98,"reanimation":5,"nouvellesHospitalisations":13,"nouvellesReanimations":0,"deces":91,"gueris":311,"source":{"nom":"Santé publique France Data"},"sourceType":"sante-publique-france-data"},{"code":"DEP-59","nom":"Nord","date":"2020-12-12","hospitalises":1060,"reanimation":125,"nouvellesHospitalisations":25,"nouvellesReanimations":5,"deces":1711,"gueris":7470,"source":{"nom":"Santé publique France Data"},"sourceType":"sante-publique-france-data"},{"code":"DEP-60","nom":"Oise","date":"2020-12-12","hospitalises":285,"reanimation":29,"nouvellesHospitalisations":7,"nouvellesReanimations":1,"deces":583,"gueris":1971,"source":{"nom":"Santé publique France Data"},"sourceType":"sante-publique-france-data"},{"code":"DEP-61","nom":"Orne","date":"2020-12-12","hospitalises":173,"reanimation":5,"nouvellesHospitalisations":2,"nouvellesReanimations":0,"deces":129,"gueris":592,"source":{"nom":"Santé publique France Data"},"sourceType":"sante-publique-france-data"},{"code":"DEP-62","nom":"Pas-de-Calais","date":"2020-12-12","hospitalises":648,"reanimation":76,"nouvellesHospitalisations":28,"nouvellesReanimations":0,"deces":789,"gueris":3467,"source":{"nom":"Santé publique France Data"},"sourceType":"sante-publique-france-data"},{"code":"DEP-63","nom":"Puy-de-Dôme","date":"2020-12-12","hospitalises":226,"reanimation":20,"nouvellesHospitalisations":6,"nouvellesReanimations":1,"deces":302,"gueris":1090,"source":{"nom":"Santé publique France Data"},"sourceType":"sante-publique-france-data"},{"code":"DEP-64","nom":"Pyrénées-Atlantiques","date":"2020-12-12","hospitalises":219,"reanimation":27,"nouvellesHospitalisations":15,"nouvellesReanimations":1,"deces":248,"gueris":1112,"source":{"nom":"Santé publique France Data"},"sourceType":"sante-publique-france-data"},{"code":"DEP-65","nom":"Hautes-Pyrénées","date":"2020-12-12","hospitalises":130,"reanimation":12,"nouvellesHospitalisations":6,"nouvellesReanimations":0,"deces":103,"gueris":486,"source":{"nom":"Santé publique France Data"},"sourceType":"sante-publique-france-data"},{"code":"DEP-66","nom":"Pyrénées-Orientales","date":"2020-12-12","hospitalises":53,"reanimation":9,"nouvellesHospitalisations":0,"nouvellesReanimations":0,"deces":116,"gueris":588,"source":{"nom":"Santé publique France Data"},"sourceType":"sante-publique-france-data"},{"code":"DEP-67","nom":"Bas-Rhin","date":"2020-12-12","hospitalises":440,"reanimation":43,"nouvellesHospitalisations":26,"nouvellesReanimations":2,"deces":955,"gueris":3913,"source":{"nom":"Santé publique France Data"},"sourceType":"sante-publique-france-data"},{"code":"DEP-68","nom":"Haut-Rhin","date":"2020-12-12","hospitalises":342,"reanimation":39,"nouvellesHospitalisations":18,"nouvellesReanimations":8,"deces":960,"gueris":3858,"source":{"nom":"Santé publique France Data"},"sourceType":"sante-publique-france-data"},{"code":"DEP-69","nom":"Rhône","date":"2020-12-12","hospitalises":1144,"reanimation":143,"nouvellesHospitalisations":30,"nouvellesReanimations":5,"deces":1672,"gueris":8170,"source":{"nom":"Santé publique France Data"},"sourceType":"sante-publique-france-data"},{"code":"DEP-70","nom":"Haute-Saône","date":"2020-12-12","hospitalises":77,"reanimation":7,"nouvellesHospitalisations":3,"nouvellesReanimations":0,"deces":131,"gueris":562,"source":{"nom":"Santé publique France Data"},"sourceType":"sante-publique-france-data"},{"code":"DEP-71","nom":"Saône-et-Loire","date":"2020-12-12","hospitalises":447,"reanimation":38,"nouvellesHospitalisations":13,"nouvellesReanimations":2,"deces":569,"gueris":2030,"source":{"nom":"Santé publique France Data"},"sourceType":"sante-publique-france-data"},{"code":"DEP-72","nom":"Sarthe","date":"2020-12-12","hospitalises":288,"reanimation":12,"nouvellesHospitalisations":14,"nouvellesReanimations":0,"deces":202,"gueris":1014,"source":{"nom":"Santé publique France Data"},"sourceType":"sante-publique-france-data"},{"code":"DEP-73","nom":"Savoie","date":"2020-12-12","hospitalises":235,"reanimation":28,"nouvellesHospitalisations":8,"nouvellesReanimations":3,"deces":414,"gueris":1567,"source":{"nom":"Santé publique France Data"},"sourceType":"sante-publique-france-data"},{"code":"DEP-74","nom":"Haute-Savoie","date":"2020-12-12","hospitalises":445,"reanimation":54,"nouvellesHospitalisations":15,"nouvellesReanimations":5,"deces":550,"gueris":2609,"source":{"nom":"Santé publique France Data"},"sourceType":"sante-publique-france-data"},{"code":"DEP-75","nom":"Paris","date":"2020-12-12","hospitalises":764,"reanimation":143,"nouvellesHospitalisations":44,"nouvellesReanimations":8,"deces":2572,"gueris":10629,"source":{"nom":"Santé publique France Data"},"sourceType":"sante-publique-france-data"},{"code":"DEP-76","nom":"Seine-Maritime","date":"2020-12-12","hospitalises":441,"reanimation":53,"nouvellesHospitalisations":24,"nouvellesReanimations":4,"deces":604,"gueris":2356,"source":{"nom":"Santé publique France Data"},"sourceType":"sante-publique-france-data"},{"code":"DEP-77","nom":"Seine-et-Marne","date":"2020-12-12","hospitalises":426,"reanimation":68,"nouvellesHospitalisations":18,"nouvellesReanimations":1,"deces":1102,"gueris":4688,"source":{"nom":"Santé publique France Data"},"sourceType":"sante-publique-france-data"},{"code":"DEP-78","nom":"Yvelines","date":"2020-12-12","hospitalises":783,"reanimation":57,"nouvellesHospitalisations":30,"nouvellesReanimations":3,"deces":969,"gueris":4243,"source":{"nom":"Santé publique France Data"},"sourceType":"sante-publique-france-data"},{"code":"DEP-79","nom":"Deux-Sèvres","date":"2020-12-12","hospitalises":59,"reanimation":6,"nouvellesHospitalisations":5,"nouvellesReanimations":1,"deces":86,"gueris":283,"source":{"nom":"Santé publique France Data"},"sourceType":"sante-publique-france-data"},{"code":"DEP-80","nom":"Somme","date":"2020-12-12","hospitalises":230,"reanimation":29,"nouvellesHospitalisations":8,"nouvellesReanimations":0,"deces":368,"gueris":1221,"source":{"nom":"Santé publique France Data"},"sourceType":"sante-publique-france-data"},{"code":"DEP-81","nom":"Tarn","date":"2020-12-12","hospitalises":151,"reanimation":20,"nouvellesHospitalisations":10,"nouvellesReanimations":2,"deces":122,"gueris":496,"source":{"nom":"Santé publique France Data"},"sourceType":"sante-publique-france-data"},{"code":"DEP-82","nom":"Tarn-et-Garonne","date":"2020-12-12","hospitalises":56,"reanimation":7,"nouvellesHospitalisations":2,"nouvellesReanimations":1,"deces":81,"gueris":380,"source":{"nom":"Santé publique France Data"},"sourceType":"sante-publique-france-data"},{"code":"DEP-83","nom":"Var","date":"2020-12-12","hospitalises":267,"reanimation":39,"nouvellesHospitalisations":9,"nouvellesReanimations":0,"deces":428,"gueris":2305,"source":{"nom":"Santé publique France Data"},"sourceType":"sante-publique-france-data"},{"code":"DEP-84","nom":"Vaucluse","date":"2020-12-12","hospitalises":265,"reanimation":15,"nouvellesHospitalisations":4,"nouvellesReanimations":0,"deces":377,"gueris":1491,"source":{"nom":"Santé publique France Data"},"sourceType":"sante-publique-france-data"},{"code":"DEP-85","nom":"Vendée","date":"2020-12-12","hospitalises":83,"reanimation":7,"nouvellesHospitalisations":4,"nouvellesReanimations":0,"deces":105,"gueris":627,"source":{"nom":"Santé publique France Data"},"sourceType":"sante-publique-france-data"},{"code":"DEP-86","nom":"Vienne","date":"2020-12-12","hospitalises":47,"reanimation":8,"nouvellesHospitalisations":8,"nouvellesReanimations":0,"deces":124,"gueris":501,"source":{"nom":"Santé publique France Data"},"sourceType":"sante-publique-france-data"},{"code":"DEP-87","nom":"Haute-Vienne","date":"2020-12-12","hospitalises":241,"reanimation":5,"nouvellesHospitalisations":0,"nouvellesReanimations":0,"deces":139,"gueris":477,"source":{"nom":"Santé publique France Data"},"sourceType":"sante-publique-france-data"},{"code":"DEP-88","nom":"Vosges","date":"2020-12-12","hospitalises":273,"reanimation":14,"nouvellesHospitalisations":24,"nouvellesReanimations":1,"deces":422,"gueris":1249,"source":{"nom":"Santé publique France Data"},"sourceType":"sante-publique-france-data"},{"code":"DEP-89","nom":"Yonne","date":"2020-12-12","hospitalises":228,"reanimation":22,"nouvellesHospitalisations":22,"nouvellesReanimations":1,"deces":198,"gueris":903,"source":{"nom":"Santé publique France Data"},"sourceType":"sante-publique-france-data"},{"code":"DEP-90","nom":"Territoire de Belfort","date":"2020-12-12","hospitalises":187,"reanimation":21,"nouvellesHospitalisations":70,"nouvellesReanimations":1,"deces":328,"gueris":934,"source":{"nom":"Santé publique France Data"},"sourceType":"sante-publique-france-data"},{"code":"DEP-91","nom":"Essonne","date":"2020-12-12","hospitalises":501,"reanimation":71,"nouvellesHospitalisations":11,"nouvellesReanimations":3,"deces":968,"gueris":4752,"source":{"nom":"Santé publique France Data"},"sourceType":"sante-publique-france-data"},{"code":"DEP-92","nom":"Hauts-de-Seine","date":"2020-12-12","hospitalises":711,"reanimation":95,"nouvellesHospitalisations":24,"nouvellesReanimations":4,"deces":1511,"gueris":7864,"source":{"nom":"Santé publique France Data"},"sourceType":"sante-publique-france-data"},{"code":"DEP-93","nom":"Seine-Saint-Denis","date":"2020-12-12","hospitalises":651,"reanimation":72,"nouvellesHospitalisations":9,"nouvellesReanimations":3,"deces":1441,"gueris":7138,"source":{"nom":"Santé publique France Data"},"sourceType":"sante-publique-france-data"},{"code":"DEP-94","nom":"Val-de-Marne","date":"2020-12-12","hospitalises":669,"reanimation":59,"nouvellesHospitalisations":18,"nouvellesReanimations":0,"deces":1767,"gueris":7504,"source":{"nom":"Santé publique France Data"},"sourceType":"sante-publique-france-data"},{"code":"DEP-95","nom":"Val-d'Oise","date":"2020-12-12","hospitalises":419,"reanimation":31,"nouvellesHospitalisations":59,"nouvellesReanimations":2,"deces":1113,"gueris":4760,"source":{"nom":"Santé publique France Data"},"sourceType":"sante-publique-france-data"},{"code":"DEP-971","nom":"Guadeloupe","date":"2020-12-12","hospitalises":79,"reanimation":5,"nouvellesHospitalisations":0,"nouvellesReanimations":0,"deces":165,"gueris":727,"source":{"nom":"Santé publique France Data"},"sourceType":"sante-publique-france-data"},{"code":"DEP-972","nom":"Martinique","date":"2020-12-12","hospitalises":30,"reanimation":8,"nouvellesHospitalisations":2,"nouvellesReanimations":0,"deces":42,"gueris":348,"source":{"nom":"Santé publique France Data"},"sourceType":"sante-publique-france-data"},{"code":"DEP-973","nom":"Guyane","date":"2020-12-12","hospitalises":14,"reanimation":0,"nouvellesHospitalisations":2,"nouvellesReanimations":0,"deces":67,"gueris":1901,"source":{"nom":"Santé publique France Data"},"sourceType":"sante-publique-france-data"},{"code":"DEP-974","nom":"La Réunion","date":"2020-12-12","hospitalises":52,"reanimation":7,"nouvellesHospitalisations":3,"nouvellesReanimations":0,"deces":50,"gueris":676,"source":{"nom":"Santé publique France Data"},"sourceType":"sante-publique-france-data"},{"code":"DEP-976","nom":"Mayotte","date":"2020-12-12","hospitalises":12,"reanimation":2,"nouvellesHospitalisations":4,"nouvellesReanimations":1,"deces":38,"gueris":524,"source":{"nom":"Santé publique France Data"},"sourceType":"sante-publique-france-data"},{"code":"FRA","nom":"France","date":"2020-12-12","hospitalises":24948,"reanimation":2851,"nouvellesHospitalisations":1097,"nouvellesReanimations":127,"deces":39799,"gueris":176712,"source":{"nom":"OpenCOVID19-fr"},"sourceType":"opencovid19-fr"},{"code":"REG-01","nom":"Guadeloupe","date":"2020-12-12","hospitalises":79,"reanimation":5,"nouvellesHospitalisations":0,"nouvellesReanimations":0,"deces":165,"gueris":727,"source":{"nom":"OpenCOVID19-fr"},"sourceType":"opencovid19-fr"},{"code":"REG-02","nom":"Martinique","date":"2020-12-12","hospitalises":30,"reanimation":8,"nouvellesHospitalisations":2,"nouvellesReanimations":0,"deces":42,"gueris":348,"source":{"nom":"OpenCOVID19-fr"},"sourceType":"opencovid19-fr"},{"code":"REG-03","nom":"Guyane","date":"2020-12-12","hospitalises":14,"reanimation":0,"nouvellesHospitalisations":2,"nouvellesReanimations":0,"deces":67,"gueris":1901,"source":{"nom":"OpenCOVID19-fr"},"sourceType":"opencovid19-fr"},{"code":"REG-04","nom":"La Réunion","date":"2020-12-12","hospitalises":52,"reanimation":7,"nouvellesHospitalisations":3,"nouvellesReanimations":0,"deces":50,"gueris":676,"source":{"nom":"OpenCOVID19-fr"},"sourceType":"opencovid19-fr"},{"code":"REG-06","nom":"Mayotte","date":"2020-12-12","hospitalises":12,"reanimation":2,"nouvellesHospitalisations":4,"nouvellesReanimations":1,"deces":38,"gueris":524,"source":{"nom":"OpenCOVID19-fr"},"sourceType":"opencovid19-fr"},{"code":"REG-11","nom":"Île-de-France","date":"2020-12-12","hospitalises":4924,"reanimation":596,"nouvellesHospitalisations":213,"nouvellesReanimations":24,"deces":11443,"gueris":51578,"source":{"nom":"OpenCOVID19-fr"},"sourceType":"opencovid19-fr"},{"code":"REG-24","nom":"Centre-Val de Loire","date":"2020-12-12","hospitalises":901,"reanimation":101,"nouvellesHospitalisations":40,"nouvellesReanimations":3,"deces":1152,"gueris":4866,"source":{"nom":"OpenCOVID19-fr"},"sourceType":"opencovid19-fr"},{"code":"REG-27","nom":"Bourgogne-Franche-Comté","date":"2020-12-12","hospitalises":1739,"reanimation":182,"nouvellesHospitalisations":154,"nouvellesReanimations":12,"deces":2209,"gueris":8488,"source":{"nom":"OpenCOVID19-fr"},"sourceType":"opencovid19-fr"},{"code":"REG-28","nom":"Normandie","date":"2020-12-12","hospitalises":1040,"reanimation":87,"nouvellesHospitalisations":37,"nouvellesReanimations":5,"deces":1305,"gueris":5169,"source":{"nom":"OpenCOVID19-fr"},"sourceType":"opencovid19-fr"},{"code":"REG-32","nom":"Hauts-de-France","date":"2020-12-12","hospitalises":2451,"reanimation":284,"nouvellesHospitalisations":94,"nouvellesReanimations":8,"deces":3886,"gueris":15944,"source":{"nom":"OpenCOVID19-fr"},"sourceType":"opencovid19-fr"},{"code":"REG-44","nom":"Grand Est","date":"2020-12-12","hospitalises":2563,"reanimation":265,"nouvellesHospitalisations":136,"nouvellesReanimations":19,"deces":5229,"gueris":19182,"source":{"nom":"OpenCOVID19-fr"},"sourceType":"opencovid19-fr"},{"code":"REG-52","nom":"Pays de la Loire","date":"2020-12-12","hospitalises":917,"reanimation":84,"nouvellesHospitalisations":47,"nouvellesReanimations":2,"deces":1129,"gueris":5421,"source":{"nom":"OpenCOVID19-fr"},"sourceType":"opencovid19-fr"},{"code":"REG-53","nom":"Bretagne","date":"2020-12-12","hospitalises":569,"reanimation":57,"nouvellesHospitalisations":27,"nouvellesReanimations":1,"deces":606,"gueris":3033,"source":{"nom":"OpenCOVID19-fr"},"sourceType":"opencovid19-fr"},{"code":"REG-75","nom":"Nouvelle-Aquitaine","date":"2020-12-12","hospitalises":1344,"reanimation":157,"nouvellesHospitalisations":59,"nouvellesReanimations":4,"deces":1465,"gueris":6897,"source":{"nom":"OpenCOVID19-fr"},"sourceType":"opencovid19-fr"},{"code":"REG-76","nom":"Occitanie","date":"2020-12-12","hospitalises":1400,"reanimation":209,"nouvellesHospitalisations":55,"nouvellesReanimations":8,"deces":1884,"gueris":9222,"source":{"nom":"OpenCOVID19-fr"},"sourceType":"opencovid19-fr"},{"code":"REG-84","nom":"Auvergne-Rhône-Alpes","date":"2020-12-12","hospitalises":4587,"reanimation":498,"nouvellesHospitalisations":139,"nouvellesReanimations":27,"deces":5937,"gueris":25148,"source":{"nom":"OpenCOVID19-fr"},"sourceType":"opencovid19-fr"},{"code":"REG-93","nom":"Provence-Alpes-Côte d'Azur","date":"2020-12-12","hospitalises":2297,"reanimation":303,"nouvellesHospitalisations":85,"nouvellesReanimations":13,"deces":3079,"gueris":17101,"source":{"nom":"OpenCOVID19-fr"},"sourceType":"opencovid19-fr"},{"code":"REG-94","nom":"Corse","date":"2020-12-12","hospitalises":29,"reanimation":6,"nouvellesHospitalisations":0,"nouvellesReanimations":0,"deces":113,"gueris":487,"source":{"nom":"OpenCOVID19-fr"},"sourceType":"opencovid19-fr"}]}