{"allFranceDataByDate":[{"code":"DEP-01","nom":"Ain","date":"2020-10-20","hospitalises":106,"reanimation":10,"nouvellesHospitalisations":33,"nouvellesReanimations":2,"deces":121,"gueris":568,"source":{"nom":"Santé publique France Data"},"sourceType":"sante-publique-france-data"},{"code":"DEP-02","nom":"Aisne","date":"2020-10-20","hospitalises":87,"reanimation":12,"nouvellesHospitalisations":8,"nouvellesReanimations":1,"deces":297,"gueris":1227,"source":{"nom":"Santé publique France Data"},"sourceType":"sante-publique-france-data"},{"code":"DEP-03","nom":"Allier","date":"2020-10-20","hospitalises":92,"reanimation":7,"nouvellesHospitalisations":18,"nouvellesReanimations":0,"deces":56,"gueris":271,"source":{"nom":"Santé publique France Data"},"sourceType":"sante-publique-france-data"},{"code":"DEP-04","nom":"Alpes-de-Haute-Provence","date":"2020-10-20","hospitalises":19,"reanimation":5,"nouvellesHospitalisations":2,"nouvellesReanimations":0,"deces":18,"gueris":177,"source":{"nom":"Santé publique France Data"},"sourceType":"sante-publique-france-data"},{"code":"DEP-05","nom":"Hautes-Alpes","date":"2020-10-20","hospitalises":53,"reanimation":7,"nouvellesHospitalisations":16,"nouvellesReanimations":0,"deces":26,"gueris":179,"source":{"nom":"Santé publique France Data"},"sourceType":"sante-publique-france-data"},{"code":"DEP-06","nom":"Alpes-Maritimes","date":"2020-10-20","hospitalises":193,"reanimation":37,"nouvellesHospitalisations":22,"nouvellesReanimations":4,"deces":235,"gueris":1286,"source":{"nom":"Santé publique France Data"},"sourceType":"sante-publique-france-data"},{"code":"DEP-07","nom":"Ardèche","date":"2020-10-20","hospitalises":71,"reanimation":7,"nouvellesHospitalisations":13,"nouvellesReanimations":1,"deces":124,"gueris":486,"source":{"nom":"Santé publique France Data"},"sourceType":"sante-publique-france-data"},{"code":"DEP-08","nom":"Ardennes","date":"2020-10-20","hospitalises":23,"reanimation":6,"nouvellesHospitalisations":1,"nouvellesReanimations":0,"deces":66,"gueris":250,"source":{"nom":"Santé publique France Data"},"sourceType":"sante-publique-france-data"},{"code":"DEP-09","nom":"Ariège","date":"2020-10-20","hospitalises":20,"reanimation":8,"nouvellesHospitalisations":0,"nouvellesReanimations":0,"deces":5,"gueris":48,"source":{"nom":"Santé publique France Data"},"sourceType":"sante-publique-france-data"},{"code":"DEP-10","nom":"Aube","date":"2020-10-20","hospitalises":45,"reanimation":3,"nouvellesHospitalisations":15,"nouvellesReanimations":1,"deces":140,"gueris":696,"source":{"nom":"Santé publique France Data"},"sourceType":"sante-publique-france-data"},{"code":"DEP-11","nom":"Aude","date":"2020-10-20","hospitalises":28,"reanimation":4,"nouvellesHospitalisations":6,"nouvellesReanimations":1,"deces":64,"gueris":274,"source":{"nom":"Santé publique France Data"},"sourceType":"sante-publique-france-data"},{"code":"DEP-12","nom":"Aveyron","date":"2020-10-20","hospitalises":34,"reanimation":2,"nouvellesHospitalisations":0,"nouvellesReanimations":0,"deces":35,"gueris":192,"source":{"nom":"Santé publique France Data"},"sourceType":"sante-publique-france-data"},{"code":"DEP-13","nom":"Bouches-du-Rhône","date":"2020-10-20","hospitalises":809,"reanimation":165,"nouvellesHospitalisations":133,"nouvellesReanimations":11,"deces":785,"gueris":5995,"source":{"nom":"Santé publique France Data"},"sourceType":"sante-publique-france-data"},{"code":"DEP-14","nom":"Calvados","date":"2020-10-20","hospitalises":92,"reanimation":23,"nouvellesHospitalisations":13,"nouvellesReanimations":2,"deces":97,"gueris":454,"source":{"nom":"Santé publique France Data"},"sourceType":"sante-publique-france-data"},{"code":"DEP-15","nom":"Cantal","date":"2020-10-20","hospitalises":36,"reanimation":4,"nouvellesHospitalisations":0,"nouvellesReanimations":0,"deces":22,"gueris":86,"source":{"nom":"Santé publique France Data"},"sourceType":"sante-publique-france-data"},{"code":"DEP-16","nom":"Charente","date":"2020-10-20","hospitalises":6,"reanimation":2,"nouvellesHospitalisations":2,"nouvellesReanimations":1,"deces":18,"gueris":78,"source":{"nom":"Santé publique France Data"},"sourceType":"sante-publique-france-data"},{"code":"DEP-17","nom":"Charente-Maritime","date":"2020-10-20","hospitalises":40,"reanimation":5,"nouvellesHospitalisations":11,"nouvellesReanimations":0,"deces":60,"gueris":191,"source":{"nom":"Santé publique France Data"},"sourceType":"sante-publique-france-data"},{"code":"DEP-18","nom":"Cher","date":"2020-10-20","hospitalises":52,"reanimation":4,"nouvellesHospitalisations":10,"nouvellesReanimations":1,"deces":103,"gueris":238,"source":{"nom":"Santé publique France Data"},"sourceType":"sante-publique-france-data"},{"code":"DEP-19","nom":"Corrèze","date":"2020-10-20","hospitalises":24,"reanimation":5,"nouvellesHospitalisations":5,"nouvellesReanimations":1,"deces":44,"gueris":189,"source":{"nom":"Santé publique France Data"},"sourceType":"sante-publique-france-data"},{"code":"DEP-21","nom":"Côte-d'Or","date":"2020-10-20","hospitalises":69,"reanimation":14,"nouvellesHospitalisations":14,"nouvellesReanimations":1,"deces":270,"gueris":1040,"source":{"nom":"Santé publique France Data"},"sourceType":"sante-publique-france-data"},{"code":"DEP-22","nom":"Côtes-d'Armor","date":"2020-10-20","hospitalises":27,"reanimation":2,"nouvellesHospitalisations":0,"nouvellesReanimations":0,"deces":43,"gueris":275,"source":{"nom":"Santé publique France Data"},"sourceType":"sante-publique-france-data"},{"code":"DEP-23","nom":"Creuse","date":"2020-10-20","hospitalises":15,"reanimation":4,"nouvellesHospitalisations":3,"nouvellesReanimations":1,"deces":17,"gueris":95,"source":{"nom":"Santé publique France Data"},"sourceType":"sante-publique-france-data"},{"code":"DEP-24","nom":"Dordogne","date":"2020-10-20","hospitalises":23,"reanimation":1,"nouvellesHospitalisations":0,"nouvellesReanimations":0,"deces":14,"gueris":122,"source":{"nom":"Santé publique France Data"},"sourceType":"sante-publique-france-data"},{"code":"DEP-25","nom":"Doubs","date":"2020-10-20","hospitalises":32,"reanimation":9,"nouvellesHospitalisations":6,"nouvellesReanimations":0,"deces":155,"gueris":680,"source":{"nom":"Santé publique France Data"},"sourceType":"sante-publique-france-data"},{"code":"DEP-26","nom":"Drôme","date":"2020-10-20","hospitalises":109,"reanimation":16,"nouvellesHospitalisations":18,"nouvellesReanimations":2,"deces":144,"gueris":616,"source":{"nom":"Santé publique France Data"},"sourceType":"sante-publique-france-data"},{"code":"DEP-27","nom":"Eure","date":"2020-10-20","hospitalises":92,"reanimation":8,"nouvellesHospitalisations":6,"nouvellesReanimations":1,"deces":104,"gueris":368,"source":{"nom":"Santé publique France Data"},"sourceType":"sante-publique-france-data"},{"code":"DEP-28","nom":"Eure-et-Loir","date":"2020-10-20","hospitalises":52,"reanimation":12,"nouvellesHospitalisations":4,"nouvellesReanimations":1,"deces":151,"gueris":691,"source":{"nom":"Santé publique France Data"},"sourceType":"sante-publique-france-data"},{"code":"DEP-29","nom":"Finistère","date":"2020-10-20","hospitalises":38,"reanimation":6,"nouvellesHospitalisations":8,"nouvellesReanimations":2,"deces":50,"gueris":250,"source":{"nom":"Santé publique France Data"},"sourceType":"sante-publique-france-data"},{"code":"DEP-2A","nom":"Corse-du-Sud","date":"2020-10-20","hospitalises":16,"reanimation":4,"nouvellesHospitalisations":1,"nouvellesReanimations":0,"deces":52,"gueris":179,"source":{"nom":"Santé publique France Data"},"sourceType":"sante-publique-france-data"},{"code":"DEP-2B","nom":"Haute-Corse","date":"2020-10-20","hospitalises":26,"reanimation":5,"nouvellesHospitalisations":1,"nouvellesReanimations":0,"deces":16,"gueris":143,"source":{"nom":"Santé publique France Data"},"sourceType":"sante-publique-france-data"},{"code":"DEP-30","nom":"Gard","date":"2020-10-20","hospitalises":132,"reanimation":31,"nouvellesHospitalisations":16,"nouvellesReanimations":3,"deces":130,"gueris":530,"source":{"nom":"Santé publique France Data"},"sourceType":"sante-publique-france-data"},{"code":"DEP-31","nom":"Haute-Garonne","date":"2020-10-20","hospitalises":189,"reanimation":56,"nouvellesHospitalisations":18,"nouvellesReanimations":5,"deces":129,"gueris":1253,"source":{"nom":"Santé publique France Data"},"sourceType":"sante-publique-france-data"},{"code":"DEP-32","nom":"Gers","date":"2020-10-20","hospitalises":20,"reanimation":3,"nouvellesHospitalisations":3,"nouvellesReanimations":1,"deces":33,"gueris":106,"source":{"nom":"Santé publique France Data"},"sourceType":"sante-publique-france-data"},{"code":"DEP-33","nom":"Gironde","date":"2020-10-20","hospitalises":209,"reanimation":28,"nouvellesHospitalisations":35,"nouvellesReanimations":5,"deces":239,"gueris":1465,"source":{"nom":"Santé publique France Data"},"sourceType":"sante-publique-france-data"},{"code":"DEP-34","nom":"Hérault","date":"2020-10-20","hospitalises":218,"reanimation":56,"nouvellesHospitalisations":32,"nouvellesReanimations":7,"deces":189,"gueris":1109,"source":{"nom":"Santé publique France Data"},"sourceType":"sante-publique-france-data"},{"code":"DEP-35","nom":"Ille-et-Vilaine","date":"2020-10-20","hospitalises":107,"reanimation":16,"nouvellesHospitalisations":17,"nouvellesReanimations":1,"deces":110,"gueris":669,"source":{"nom":"Santé publique France Data"},"sourceType":"sante-publique-france-data"},{"code":"DEP-36","nom":"Indre","date":"2020-10-20","hospitalises":21,"reanimation":6,"nouvellesHospitalisations":6,"nouvellesReanimations":1,"deces":82,"gueris":213,"source":{"nom":"Santé publique France Data"},"sourceType":"sante-publique-france-data"},{"code":"DEP-37","nom":"Indre-et-Loire","date":"2020-10-20","hospitalises":48,"reanimation":11,"nouvellesHospitalisations":8,"nouvellesReanimations":4,"deces":105,"gueris":491,"source":{"nom":"Santé publique France Data"},"sourceType":"sante-publique-france-data"},{"code":"DEP-38","nom":"Isère","date":"2020-10-20","hospitalises":344,"reanimation":60,"nouvellesHospitalisations":68,"nouvellesReanimations":12,"deces":215,"gueris":1148,"source":{"nom":"Santé publique France Data"},"sourceType":"sante-publique-france-data"},{"code":"DEP-39","nom":"Jura","date":"2020-10-20","hospitalises":48,"reanimation":2,"nouvellesHospitalisations":9,"nouvellesReanimations":0,"deces":62,"gueris":359,"source":{"nom":"Santé publique France Data"},"sourceType":"sante-publique-france-data"},{"code":"DEP-40","nom":"Landes","date":"2020-10-20","hospitalises":55,"reanimation":3,"nouvellesHospitalisations":16,"nouvellesReanimations":0,"deces":22,"gueris":115,"source":{"nom":"Santé publique France Data"},"sourceType":"sante-publique-france-data"},{"code":"DEP-41","nom":"Loir-et-Cher","date":"2020-10-20","hospitalises":20,"reanimation":1,"nouvellesHospitalisations":7,"nouvellesReanimations":2,"deces":72,"gueris":379,"source":{"nom":"Santé publique France Data"},"sourceType":"sante-publique-france-data"},{"code":"DEP-42","nom":"Loire","date":"2020-10-20","hospitalises":418,"reanimation":58,"nouvellesHospitalisations":56,"nouvellesReanimations":7,"deces":330,"gueris":1337,"source":{"nom":"Santé publique France Data"},"sourceType":"sante-publique-france-data"},{"code":"DEP-43","nom":"Haute-Loire","date":"2020-10-20","hospitalises":40,"reanimation":2,"nouvellesHospitalisations":17,"nouvellesReanimations":0,"deces":25,"gueris":154,"source":{"nom":"Santé publique France Data"},"sourceType":"sante-publique-france-data"},{"code":"DEP-44","nom":"Loire-Atlantique","date":"2020-10-20","hospitalises":125,"reanimation":21,"nouvellesHospitalisations":11,"nouvellesReanimations":2,"deces":195,"gueris":944,"source":{"nom":"Santé publique France Data"},"sourceType":"sante-publique-france-data"},{"code":"DEP-45","nom":"Loiret","date":"2020-10-20","hospitalises":89,"reanimation":29,"nouvellesHospitalisations":8,"nouvellesReanimations":5,"deces":114,"gueris":784,"source":{"nom":"Santé publique France Data"},"sourceType":"sante-publique-france-data"},{"code":"DEP-46","nom":"Lot","date":"2020-10-20","hospitalises":7,"reanimation":2,"nouvellesHospitalisations":1,"nouvellesReanimations":0,"deces":22,"gueris":76,"source":{"nom":"Santé publique France Data"},"sourceType":"sante-publique-france-data"},{"code":"DEP-47","nom":"Lot-et-Garonne","date":"2020-10-20","hospitalises":24,"reanimation":4,"nouvellesHospitalisations":2,"nouvellesReanimations":1,"deces":19,"gueris":138,"source":{"nom":"Santé publique France Data"},"sourceType":"sante-publique-france-data"},{"code":"DEP-48","nom":"Lozère","date":"2020-10-20","hospitalises":18,"reanimation":0,"nouvellesHospitalisations":2,"nouvellesReanimations":0,"deces":8,"gueris":37,"source":{"nom":"Santé publique France Data"},"sourceType":"sante-publique-france-data"},{"code":"DEP-49","nom":"Maine-et-Loire","date":"2020-10-20","hospitalises":104,"reanimation":19,"nouvellesHospitalisations":16,"nouvellesReanimations":6,"deces":161,"gueris":831,"source":{"nom":"Santé publique France Data"},"sourceType":"sante-publique-france-data"},{"code":"DEP-50","nom":"Manche","date":"2020-10-20","hospitalises":37,"reanimation":6,"nouvellesHospitalisations":4,"nouvellesReanimations":0,"deces":61,"gueris":219,"source":{"nom":"Santé publique France Data"},"sourceType":"sante-publique-france-data"},{"code":"DEP-51","nom":"Marne","date":"2020-10-20","hospitalises":76,"reanimation":16,"nouvellesHospitalisations":23,"nouvellesReanimations":5,"deces":295,"gueris":1165,"source":{"nom":"Santé publique France Data"},"sourceType":"sante-publique-france-data"},{"code":"DEP-52","nom":"Haute-Marne","date":"2020-10-20","hospitalises":29,"reanimation":2,"nouvellesHospitalisations":2,"nouvellesReanimations":0,"deces":96,"gueris":287,"source":{"nom":"Santé publique France Data"},"sourceType":"sante-publique-france-data"},{"code":"DEP-53","nom":"Mayenne","date":"2020-10-20","hospitalises":20,"reanimation":3,"nouvellesHospitalisations":3,"nouvellesReanimations":0,"deces":52,"gueris":285,"source":{"nom":"Santé publique France Data"},"sourceType":"sante-publique-france-data"},{"code":"DEP-54","nom":"Meurthe-et-Moselle","date":"2020-10-20","hospitalises":62,"reanimation":8,"nouvellesHospitalisations":4,"nouvellesReanimations":0,"deces":377,"gueris":1410,"source":{"nom":"Santé publique France Data"},"sourceType":"sante-publique-france-data"},{"code":"DEP-55","nom":"Meuse","date":"2020-10-20","hospitalises":22,"reanimation":1,"nouvellesHospitalisations":5,"nouvellesReanimations":1,"deces":106,"gueris":530,"source":{"nom":"Santé publique France Data"},"sourceType":"sante-publique-france-data"},{"code":"DEP-56","nom":"Morbihan","date":"2020-10-20","hospitalises":65,"reanimation":6,"nouvellesHospitalisations":4,"nouvellesReanimations":1,"deces":105,"gueris":522,"source":{"nom":"Santé publique France Data"},"sourceType":"sante-publique-france-data"},{"code":"DEP-57","nom":"Moselle","date":"2020-10-20","hospitalises":104,"reanimation":18,"nouvellesHospitalisations":32,"nouvellesReanimations":3,"deces":878,"gueris":2763,"source":{"nom":"Santé publique France Data"},"sourceType":"sante-publique-france-data"},{"code":"DEP-58","nom":"Nièvre","date":"2020-10-20","hospitalises":15,"reanimation":4,"nouvellesHospitalisations":0,"nouvellesReanimations":0,"deces":29,"gueris":127,"source":{"nom":"Santé publique France Data"},"sourceType":"sante-publique-france-data"},{"code":"DEP-59","nom":"Nord","date":"2020-10-20","hospitalises":801,"reanimation":141,"nouvellesHospitalisations":158,"nouvellesReanimations":20,"deces":820,"gueris":3568,"source":{"nom":"Santé publique France Data"},"sourceType":"sante-publique-france-data"},{"code":"DEP-60","nom":"Oise","date":"2020-10-20","hospitalises":134,"reanimation":20,"nouvellesHospitalisations":11,"nouvellesReanimations":0,"deces":450,"gueris":1382,"source":{"nom":"Santé publique France Data"},"sourceType":"sante-publique-france-data"},{"code":"DEP-61","nom":"Orne","date":"2020-10-20","hospitalises":22,"reanimation":3,"nouvellesHospitalisations":3,"nouvellesReanimations":1,"deces":51,"gueris":292,"source":{"nom":"Santé publique France Data"},"sourceType":"sante-publique-france-data"},{"code":"DEP-62","nom":"Pas-de-Calais","date":"2020-10-20","hospitalises":251,"reanimation":32,"nouvellesHospitalisations":37,"nouvellesReanimations":4,"deces":373,"gueris":1805,"source":{"nom":"Santé publique France Data"},"sourceType":"sante-publique-france-data"},{"code":"DEP-63","nom":"Puy-de-Dôme","date":"2020-10-20","hospitalises":163,"reanimation":16,"nouvellesHospitalisations":20,"nouvellesReanimations":4,"deces":73,"gueris":331,"source":{"nom":"Santé publique France Data"},"sourceType":"sante-publique-france-data"},{"code":"DEP-64","nom":"Pyrénées-Atlantiques","date":"2020-10-20","hospitalises":61,"reanimation":10,"nouvellesHospitalisations":6,"nouvellesReanimations":2,"deces":45,"gueris":354,"source":{"nom":"Santé publique France Data"},"sourceType":"sante-publique-france-data"},{"code":"DEP-65","nom":"Hautes-Pyrénées","date":"2020-10-20","hospitalises":24,"reanimation":6,"nouvellesHospitalisations":1,"nouvellesReanimations":0,"deces":27,"gueris":186,"source":{"nom":"Santé publique France Data"},"sourceType":"sante-publique-france-data"},{"code":"DEP-66","nom":"Pyrénées-Orientales","date":"2020-10-20","hospitalises":46,"reanimation":9,"nouvellesHospitalisations":7,"nouvellesReanimations":1,"deces":45,"gueris":346,"source":{"nom":"Santé publique France Data"},"sourceType":"sante-publique-france-data"},{"code":"DEP-67","nom":"Bas-Rhin","date":"2020-10-20","hospitalises":95,"reanimation":10,"nouvellesHospitalisations":26,"nouvellesReanimations":2,"deces":715,"gueris":2960,"source":{"nom":"Santé publique France Data"},"sourceType":"sante-publique-france-data"},{"code":"DEP-68","nom":"Haut-Rhin","date":"2020-10-20","hospitalises":45,"reanimation":7,"nouvellesHospitalisations":11,"nouvellesReanimations":0,"deces":845,"gueris":3278,"source":{"nom":"Santé publique France Data"},"sourceType":"sante-publique-france-data"},{"code":"DEP-69","nom":"Rhône","date":"2020-10-20","hospitalises":788,"reanimation":135,"nouvellesHospitalisations":177,"nouvellesReanimations":13,"deces":826,"gueris":4323,"source":{"nom":"Santé publique France Data"},"sourceType":"sante-publique-france-data"},{"code":"DEP-70","nom":"Haute-Saône","date":"2020-10-20","hospitalises":22,"reanimation":1,"nouvellesHospitalisations":5,"nouvellesReanimations":0,"deces":82,"gueris":322,"source":{"nom":"Santé publique France Data"},"sourceType":"sante-publique-france-data"},{"code":"DEP-71","nom":"Saône-et-Loire","date":"2020-10-20","hospitalises":147,"reanimation":15,"nouvellesHospitalisations":35,"nouvellesReanimations":4,"deces":234,"gueris":937,"source":{"nom":"Santé publique France Data"},"sourceType":"sante-publique-france-data"},{"code":"DEP-72","nom":"Sarthe","date":"2020-10-20","hospitalises":71,"reanimation":4,"nouvellesHospitalisations":12,"nouvellesReanimations":1,"deces":100,"gueris":560,"source":{"nom":"Santé publique France Data"},"sourceType":"sante-publique-france-data"},{"code":"DEP-73","nom":"Savoie","date":"2020-10-20","hospitalises":108,"reanimation":10,"nouvellesHospitalisations":12,"nouvellesReanimations":1,"deces":92,"gueris":519,"source":{"nom":"Santé publique France Data"},"sourceType":"sante-publique-france-data"},{"code":"DEP-74","nom":"Haute-Savoie","date":"2020-10-20","hospitalises":89,"reanimation":15,"nouvellesHospitalisations":17,"nouvellesReanimations":6,"deces":182,"gueris":1066,"source":{"nom":"Santé publique France Data"},"sourceType":"sante-publique-france-data"},{"code":"DEP-75","nom":"Paris","date":"2020-10-20","hospitalises":703,"reanimation":158,"nouvellesHospitalisations":91,"nouvellesReanimations":21,"deces":1983,"gueris":7856,"source":{"nom":"Santé publique France Data"},"sourceType":"sante-publique-france-data"},{"code":"DEP-76","nom":"Seine-Maritime","date":"2020-10-20","hospitalises":286,"reanimation":42,"nouvellesHospitalisations":29,"nouvellesReanimations":4,"deces":228,"gueris":1147,"source":{"nom":"Santé publique France Data"},"sourceType":"sante-publique-france-data"},{"code":"DEP-77","nom":"Seine-et-Marne","date":"2020-10-20","hospitalises":217,"reanimation":68,"nouvellesHospitalisations":39,"nouvellesReanimations":10,"deces":774,"gueris":3332,"source":{"nom":"Santé publique France Data"},"sourceType":"sante-publique-france-data"},{"code":"DEP-78","nom":"Yvelines","date":"2020-10-20","hospitalises":321,"reanimation":42,"nouvellesHospitalisations":30,"nouvellesReanimations":7,"deces":603,"gueris":3009,"source":{"nom":"Santé publique France Data"},"sourceType":"sante-publique-france-data"},{"code":"DEP-79","nom":"Deux-Sèvres","date":"2020-10-20","hospitalises":7,"reanimation":1,"nouvellesHospitalisations":1,"nouvellesReanimations":0,"deces":26,"gueris":87,"source":{"nom":"Santé publique France Data"},"sourceType":"sante-publique-france-data"},{"code":"DEP-80","nom":"Somme","date":"2020-10-20","hospitalises":91,"reanimation":21,"nouvellesHospitalisations":9,"nouvellesReanimations":1,"deces":252,"gueris":843,"source":{"nom":"Santé publique France Data"},"sourceType":"sante-publique-france-data"},{"code":"DEP-81","nom":"Tarn","date":"2020-10-20","hospitalises":74,"reanimation":12,"nouvellesHospitalisations":4,"nouvellesReanimations":2,"deces":33,"gueris":197,"source":{"nom":"Santé publique France Data"},"sourceType":"sante-publique-france-data"},{"code":"DEP-82","nom":"Tarn-et-Garonne","date":"2020-10-20","hospitalises":56,"reanimation":12,"nouvellesHospitalisations":7,"nouvellesReanimations":3,"deces":16,"gueris":101,"source":{"nom":"Santé publique France Data"},"sourceType":"sante-publique-france-data"},{"code":"DEP-83","nom":"Var","date":"2020-10-20","hospitalises":109,"reanimation":22,"nouvellesHospitalisations":25,"nouvellesReanimations":2,"deces":172,"gueris":1284,"source":{"nom":"Santé publique France Data"},"sourceType":"sante-publique-france-data"},{"code":"DEP-84","nom":"Vaucluse","date":"2020-10-20","hospitalises":150,"reanimation":10,"nouvellesHospitalisations":23,"nouvellesReanimations":0,"deces":79,"gueris":487,"source":{"nom":"Santé publique France Data"},"sourceType":"sante-publique-france-data"},{"code":"DEP-85","nom":"Vendée","date":"2020-10-20","hospitalises":33,"reanimation":10,"nouvellesHospitalisations":7,"nouvellesReanimations":2,"deces":46,"gueris":333,"source":{"nom":"Santé publique France Data"},"sourceType":"sante-publique-france-data"},{"code":"DEP-86","nom":"Vienne","date":"2020-10-20","hospitalises":18,"reanimation":2,"nouvellesHospitalisations":7,"nouvellesReanimations":1,"deces":44,"gueris":185,"source":{"nom":"Santé publique France Data"},"sourceType":"sante-publique-france-data"},{"code":"DEP-87","nom":"Haute-Vienne","date":"2020-10-20","hospitalises":58,"reanimation":5,"nouvellesHospitalisations":5,"nouvellesReanimations":0,"deces":46,"gueris":194,"source":{"nom":"Santé publique France Data"},"sourceType":"sante-publique-france-data"},{"code":"DEP-88","nom":"Vosges","date":"2020-10-20","hospitalises":20,"reanimation":3,"nouvellesHospitalisations":8,"nouvellesReanimations":1,"deces":269,"gueris":779,"source":{"nom":"Santé publique France Data"},"sourceType":"sante-publique-france-data"},{"code":"DEP-89","nom":"Yonne","date":"2020-10-20","hospitalises":30,"reanimation":7,"nouvellesHospitalisations":3,"nouvellesReanimations":2,"deces":95,"gueris":477,"source":{"nom":"Santé publique France Data"},"sourceType":"sante-publique-france-data"},{"code":"DEP-90","nom":"Territoire de Belfort","date":"2020-10-20","hospitalises":21,"reanimation":5,"nouvellesHospitalisations":7,"nouvellesReanimations":0,"deces":202,"gueris":594,"source":{"nom":"Santé publique France Data"},"sourceType":"sante-publique-france-data"},{"code":"DEP-91","nom":"Essonne","date":"2020-10-20","hospitalises":311,"reanimation":71,"nouvellesHospitalisations":55,"nouvellesReanimations":8,"deces":674,"gueris":3342,"source":{"nom":"Santé publique France Data"},"sourceType":"sante-publique-france-data"},{"code":"DEP-92","nom":"Hauts-de-Seine","date":"2020-10-20","hospitalises":503,"reanimation":112,"nouvellesHospitalisations":75,"nouvellesReanimations":21,"deces":1204,"gueris":5956,"source":{"nom":"Santé publique France Data"},"sourceType":"sante-publique-france-data"},{"code":"DEP-93","nom":"Seine-Saint-Denis","date":"2020-10-20","hospitalises":510,"reanimation":78,"nouvellesHospitalisations":43,"nouvellesReanimations":7,"deces":1127,"gueris":5260,"source":{"nom":"Santé publique France Data"},"sourceType":"sante-publique-france-data"},{"code":"DEP-94","nom":"Val-de-Marne","date":"2020-10-20","hospitalises":518,"reanimation":94,"nouvellesHospitalisations":84,"nouvellesReanimations":14,"deces":1332,"gueris":5505,"source":{"nom":"Santé publique France Data"},"sourceType":"sante-publique-france-data"},{"code":"DEP-95","nom":"Val-d'Oise","date":"2020-10-20","hospitalises":241,"reanimation":38,"nouvellesHospitalisations":40,"nouvellesReanimations":5,"deces":818,"gueris":3451,"source":{"nom":"Santé publique France Data"},"sourceType":"sante-publique-france-data"},{"code":"DEP-971","nom":"Guadeloupe","date":"2020-10-20","hospitalises":162,"reanimation":24,"nouvellesHospitalisations":13,"nouvellesReanimations":1,"deces":124,"gueris":520,"source":{"nom":"Santé publique France Data"},"sourceType":"sante-publique-france-data"},{"code":"DEP-972","nom":"Martinique","date":"2020-10-20","hospitalises":67,"reanimation":16,"nouvellesHospitalisations":3,"nouvellesReanimations":0,"deces":27,"gueris":161,"source":{"nom":"Santé publique France Data"},"sourceType":"sante-publique-france-data"},{"code":"DEP-973","nom":"Guyane","date":"2020-10-20","hospitalises":15,"reanimation":1,"nouvellesHospitalisations":1,"nouvellesReanimations":0,"deces":65,"gueris":1767,"source":{"nom":"Santé publique France Data"},"sourceType":"sante-publique-france-data"},{"code":"DEP-974","nom":"La Réunion","date":"2020-10-20","hospitalises":43,"reanimation":8,"nouvellesHospitalisations":1,"nouvellesReanimations":1,"deces":27,"gueris":454,"source":{"nom":"Santé publique France Data"},"sourceType":"sante-publique-france-data"},{"code":"DEP-976","nom":"Mayotte","date":"2020-10-20","hospitalises":9,"reanimation":3,"nouvellesHospitalisations":1,"nouvellesReanimations":0,"deces":30,"gueris":468,"source":{"nom":"Santé publique France Data"},"sourceType":"sante-publique-france-data"},{"date":"2020-10-20","source":{"nom":"Ministère des Solidarités et de la Santé"},"sourceType":"ministere-sante","casConfirmes":930745,"deces":22873,"decesEhpad":11012,"hospitalises":12458,"reanimation":2177,"gueris":106839,"casConfirmesEhpad":53385,"nouvellesHospitalisations":1944,"nouvellesReanimations":278,"nom":"France","code":"FRA"},{"code":"FRA","nom":"France","date":"2020-10-20","hospitalises":12435,"reanimation":2168,"nouvellesHospitalisations":1943,"nouvellesReanimations":278,"deces":22849,"gueris":106808,"source":{"nom":"OpenCOVID19-fr"},"sourceType":"opencovid19-fr"},{"code":"REG-01","nom":"Guadeloupe","date":"2020-10-20","hospitalises":162,"reanimation":24,"nouvellesHospitalisations":13,"nouvellesReanimations":1,"deces":124,"gueris":520,"source":{"nom":"OpenCOVID19-fr"},"sourceType":"opencovid19-fr"},{"code":"REG-02","nom":"Martinique","date":"2020-10-20","hospitalises":67,"reanimation":16,"nouvellesHospitalisations":3,"nouvellesReanimations":0,"deces":27,"gueris":161,"source":{"nom":"OpenCOVID19-fr"},"sourceType":"opencovid19-fr"},{"code":"REG-03","nom":"Guyane","date":"2020-10-20","hospitalises":15,"reanimation":1,"nouvellesHospitalisations":1,"nouvellesReanimations":0,"deces":65,"gueris":1767,"source":{"nom":"OpenCOVID19-fr"},"sourceType":"opencovid19-fr"},{"code":"REG-04","nom":"La Réunion","date":"2020-10-20","hospitalises":43,"reanimation":8,"nouvellesHospitalisations":1,"nouvellesReanimations":1,"deces":27,"gueris":454,"source":{"nom":"OpenCOVID19-fr"},"sourceType":"opencovid19-fr"},{"code":"REG-06","nom":"Mayotte","date":"2020-10-20","hospitalises":9,"reanimation":3,"nouvellesHospitalisations":1,"nouvellesReanimations":0,"deces":30,"gueris":468,"source":{"nom":"OpenCOVID19-fr"},"sourceType":"opencovid19-fr"},{"code":"REG-11","nom":"Île-de-France","date":"2020-10-20","hospitalises":3324,"reanimation":661,"nouvellesHospitalisations":457,"nouvellesReanimations":93,"deces":8515,"gueris":37711,"source":{"nom":"OpenCOVID19-fr"},"sourceType":"opencovid19-fr"},{"code":"REG-24","nom":"Centre-Val de Loire","date":"2020-10-20","hospitalises":282,"reanimation":63,"nouvellesHospitalisations":43,"nouvellesReanimations":14,"deces":627,"gueris":2796,"source":{"nom":"OpenCOVID19-fr"},"sourceType":"opencovid19-fr"},{"code":"REG-27","nom":"Bourgogne-Franche-Comté","date":"2020-10-20","hospitalises":384,"reanimation":57,"nouvellesHospitalisations":79,"nouvellesReanimations":7,"deces":1129,"gueris":4536,"source":{"nom":"OpenCOVID19-fr"},"sourceType":"opencovid19-fr"},{"code":"REG-28","nom":"Normandie","date":"2020-10-20","hospitalises":529,"reanimation":82,"nouvellesHospitalisations":55,"nouvellesReanimations":8,"deces":541,"gueris":2480,"source":{"nom":"OpenCOVID19-fr"},"sourceType":"opencovid19-fr"},{"code":"REG-32","nom":"Hauts-de-France","date":"2020-10-20","hospitalises":1364,"reanimation":226,"nouvellesHospitalisations":223,"nouvellesReanimations":26,"deces":2192,"gueris":8825,"source":{"nom":"OpenCOVID19-fr"},"sourceType":"opencovid19-fr"},{"code":"REG-44","nom":"Grand Est","date":"2020-10-20","hospitalises":521,"reanimation":74,"nouvellesHospitalisations":127,"nouvellesReanimations":13,"deces":3787,"gueris":14118,"source":{"nom":"OpenCOVID19-fr"},"sourceType":"opencovid19-fr"},{"code":"REG-52","nom":"Pays de la Loire","date":"2020-10-20","hospitalises":353,"reanimation":57,"nouvellesHospitalisations":49,"nouvellesReanimations":11,"deces":554,"gueris":2953,"source":{"nom":"OpenCOVID19-fr"},"sourceType":"opencovid19-fr"},{"code":"REG-53","nom":"Bretagne","date":"2020-10-20","hospitalises":237,"reanimation":30,"nouvellesHospitalisations":29,"nouvellesReanimations":4,"deces":308,"gueris":1716,"source":{"nom":"OpenCOVID19-fr"},"sourceType":"opencovid19-fr"},{"code":"REG-75","nom":"Nouvelle-Aquitaine","date":"2020-10-20","hospitalises":540,"reanimation":70,"nouvellesHospitalisations":93,"nouvellesReanimations":12,"deces":594,"gueris":3213,"source":{"nom":"OpenCOVID19-fr"},"sourceType":"opencovid19-fr"},{"code":"REG-76","nom":"Occitanie","date":"2020-10-20","hospitalises":866,"reanimation":201,"nouvellesHospitalisations":97,"nouvellesReanimations":23,"deces":736,"gueris":4455,"source":{"nom":"OpenCOVID19-fr"},"sourceType":"opencovid19-fr"},{"code":"REG-84","nom":"Auvergne-Rhône-Alpes","date":"2020-10-20","hospitalises":2364,"reanimation":340,"nouvellesHospitalisations":449,"nouvellesReanimations":48,"deces":2210,"gueris":10905,"source":{"nom":"OpenCOVID19-fr"},"sourceType":"opencovid19-fr"},{"code":"REG-93","nom":"Provence-Alpes-Côte d'Azur","date":"2020-10-20","hospitalises":1333,"reanimation":246,"nouvellesHospitalisations":221,"nouvellesReanimations":17,"deces":1315,"gueris":9408,"source":{"nom":"OpenCOVID19-fr"},"sourceType":"opencovid19-fr"},{"code":"REG-94","nom":"Corse","date":"2020-10-20","hospitalises":42,"reanimation":9,"nouvellesHospitalisations":2,"nouvellesReanimations":0,"deces":68,"gueris":322,"source":{"nom":"OpenCOVID19-fr"},"sourceType":"opencovid19-fr"}]}